<?xml version="1.0" encoding="UTF-8"?>
<Product id="131651514903393980"><Catalogue cvl="Catalogue"><value><![CDATA[2012-UDS2-PAUT]]></value></Catalogue><Fitting cvl="Fitting"><![CDATA[Relaxed]]></Fitting><SizeGroup><![CDATA[<SizeRange name="S/M-L/XL-2XL/3XL">S/M,L/XL,2XL/3XL</SizeRange>]]></SizeGroup><DescriptionCatalogues><DescriptionCatalogue locale="da">Løs model. V-hals med pailletter. Smock foran. Let transparent kvalitet med print.</DescriptionCatalogue><DescriptionCatalogue locale="de_CH">Leger geschnittenes Modell. V-Ausschnitt mit Pailletten. Vorne gesmokt. Leicht transparente Qualität mit Print.</DescriptionCatalogue><DescriptionCatalogue locale="en">Loose fit. V-neck with sequins. Smocking at front. Lightweight, transparent printed fabric.</DescriptionCatalogue><DescriptionCatalogue locale="de">Leger geschnittenes Modell. V-Ausschnitt mit Pailletten. Vorne gesmokt. Leicht transparente Qualität mit Print.</DescriptionCatalogue><DescriptionCatalogue locale="nl">Los model. V-hals met pailletjes. Smock voor. Licht transparante kwaliteit met print.</DescriptionCatalogue><DescriptionCatalogue locale="sv">Lös modell. V-ringning med paljetter. Smock fram. Lätt transparent kvalitet med tryck.</DescriptionCatalogue></DescriptionCatalogues><Animal_Origin>false</Animal_Origin><MeasureHeading cvl="MeasureHeading"><value><![CDATA[Length]]></value><value><![CDATA[Size]]></value></MeasureHeading><MeasurementDescriptions><MeasurementDescription locale="da" /><MeasurementDescription locale="de_CH" /><MeasurementDescription locale="en" /><MeasurementDescription locale="de" /><MeasurementDescription locale="nl" /><MeasurementDescription locale="sv" /></MeasurementDescriptions><Program cvl="Program"><![CDATA[O]]></Program><IsLive /><Composition cvl="Composition"><![CDATA[16]]></Composition><ProductMainGroup cvl="ProductMainGroup"><![CDATA[44]]></ProductMainGroup><SizeGuide /><SizeGroupName><![CDATA[S/M-L/XL-2XL/3XL]]></SizeGroupName><MeasurementImage /><ProductStatus cvl="ProductStatus" /><translationReady /><Season cvl="Season"><value><![CDATA[122]]></value></Season><Concept cvl="Concept"><![CDATA[S]]></Concept><DisplaySize>true</DisplaySize><MeasureChartAbrv /><ProductSubGroup cvl="ProductSubGroup" /><LengthDescription cvl="LengthDescription" /><ProductGroup cvl="ProductGroup"><![CDATA[4419]]></ProductGroup><DescriptionWebs><DescriptionWeb locale="da" /><DescriptionWeb locale="de_CH" /><DescriptionWeb locale="en" /><DescriptionWeb locale="de" /><DescriptionWeb locale="nl" /><DescriptionWeb locale="sv" /></DescriptionWebs><HeaderWebs><HeaderWeb locale="da">Tunika</HeaderWeb><HeaderWeb locale="de_CH">Tunika</HeaderWeb><HeaderWeb locale="en">Tunic</HeaderWeb><HeaderWeb locale="de">Tunika</HeaderWeb><HeaderWeb locale="nl">Tuniek</HeaderWeb><HeaderWeb locale="sv">Tunika</HeaderWeb></HeaderWebs><CompositionFoders><CompositionFoder locale="da" /><CompositionFoder locale="de_CH" /><CompositionFoder locale="en" /><CompositionFoder locale="de" /><CompositionFoder locale="nl" /><CompositionFoder locale="sv" /></CompositionFoders><DescriptionPDMs><DescriptionPDM locale="da">Oversized beach tunic with smock front and sequins in the neckline front Shell fabric/Yderstof/Oberstoff 100% Polyester</DescriptionPDM><DescriptionPDM locale="de_CH" /><DescriptionPDM locale="en" /><DescriptionPDM locale="de" /><DescriptionPDM locale="nl" /><DescriptionPDM locale="sv" /></DescriptionPDMs><usedInSpread /><LengthImage /><DisplayComposition>true</DisplayComposition><StyleNbr><![CDATA[5674]]></StyleNbr><HeaderPDMs><HeaderPDM locale="da">Tunika</HeaderPDM><HeaderPDM locale="de_CH" /><HeaderPDM locale="en" /><HeaderPDM locale="de" /><HeaderPDM locale="nl" /><HeaderPDM locale="sv" /></HeaderPDMs><Items><Item id="131651514876854691"><Descriptions><Description locale="da" /><Description locale="de_CH" /><Description locale="en" /><Description locale="de" /><Description locale="nl" /><Description locale="sv" /></Descriptions><AdCodes><![CDATA[<AdCode catalogue="2012-UDS2-PAUT">9</AdCode>]]></AdCodes><CinoNumber><![CDATA[14527]]></CinoNumber><Prices><![CDATA[<Catalogue name="2012-UDS2-PAUT"><Country code="DK" currency="DKK"><Size name="S/M">129.95</Size><Size name="L/XL">129.95</Size><Size name="2XL/3XL">129.95</Size></Country><Country code="SE" currency="SEK"><Size name="S/M">179.95</Size><Size name="L/XL">179.95</Size><Size name="2XL/3XL">179.95</Size></Country><Country code="NL" currency="EUR"><Size name="S/M">19.95</Size><Size name="L/XL">19.95</Size><Size name="2XL/3XL">19.95</Size></Country><Country code="DE" currency="EUR"><Size name="S/M">19.95</Size><Size name="L/XL">19.95</Size><Size name="2XL/3XL">19.95</Size></Country><Country code="CH" currency="SFR"><Size name="S/M">39.95</Size><Size name="L/XL">39.95</Size><Size name="2XL/3XL">39.95</Size></Country><Country code="GB" currency="GBP"><Size name="/M">20.00</Size><Size name="L/XL">20.00</Size><Size name="2XL/3XL">20.00</Size></Country></Catalogue>]]></Prices><Portals><Portal locale="da" /><Portal locale="de_CH" /><Portal locale="en" /><Portal locale="de" /><Portal locale="nl" /><Portal locale="sv" /></Portals><WashTemperature cvl="WashIcon" /><Inspirations><Inspiration locale="da" /><Inspiration locale="de_CH" /><Inspiration locale="en" /><Inspiration locale="de" /><Inspiration locale="nl" /><Inspiration locale="sv" /></Inspirations><Color cvl="Color"><![CDATA[2179]]></Color><ProductSubGroup /><Sizess><Sizes locale="da">S/M-L/XL-2XL/3XL</Sizes><Sizes locale="de_CH">S/M-L/XL-2XL/3XL</Sizes><Sizes locale="en">S/M-L/XL-2XL/3XL</Sizes><Sizes locale="de">S/M-L/XL-2XL/3XL</Sizes><Sizes locale="nl">S/M-L/XL-2XL/3XL</Sizes><Sizes locale="sv">S/M-L/XL-2XL/3XL</Sizes></Sizess><WashIcon cvl="WashIcon"><value><![CDATA[10300]]></value><value><![CDATA[20100]]></value><value><![CDATA[50150]]></value><value><![CDATA[30200]]></value><value><![CDATA[40100]]></value></WashIcon><ColorGroup><![CDATA[Red]]></ColorGroup><MeasurementChart /><Length /><ActiveCatalogue cvl="Catalogue"><value><![CDATA[2012-UDS2-PAUT]]></value></ActiveCatalogue><LengthChart /><WashInstructions><WashInstruction locale="da">Vaskes med vrangen ud med lignende farver, uden optisk hvidt. Undlad iblødsætning. Strækkes i facon i våd tilstand. Hængetørring. Stryges på bagsiden. Krymp 1-3%</WashInstruction><WashInstruction locale="de_CH">Von links waschen mit ähnlichen Farben. Buntwaschmittel ohne optische Aufheller. Nicht einweichen. In nassem Zustand in Form ziehen. Hängend trocknen. Von links bügeln. Läuft ein 1-3%</WashInstruction><WashInstruction locale="en">Wash inside out with similar colours, w/o optical white. No soaking. To be stretched in shape while wet. Hang dry. Iron on backside. Shrink 1-3%</WashInstruction><WashInstruction locale="de">Von links waschen mit ähnlichen Farben. Buntwaschmittel ohne optische Aufheller. Nicht einweichen. In nassem Zustand in Form ziehen. Hängend trocknen. Von links bügeln. Läuft ein 1-3%</WashInstruction><WashInstruction locale="nl">Binnenste buiten wassen met dezelfde kleuren, zonder optisch wit. Niet weken. In vochtige toestand, voorzichtig op maat rekken. Hangend drogen. Binnenste buiten strijken. Krimp: 1 - 3%.</WashInstruction><WashInstruction locale="sv">Tvättas med avigsidan ut med liknande färger och utan optiskt vitmedel. Undvik blötläggning. Sträcks försiktigt i vått tillstånd. Ska hängtorka. Strykes på baksidan. Krymper: 1 - 3%.</WashInstruction></WashInstructions><IsLive /><LeadPicture><Resource id="131884142465833567_44861" /></LeadPicture><Resources><Resource id="131884142465833567_44861"><Year cvl="Year"><![CDATA[12]]></Year><PDMIdentifier /><CatalogAdcode cvl="CatalogAdcode"><value><![CDATA[2012-BAP-Prespring]]></value><value><![CDATA[2012-Secrets-Sum]]></value><value><![CDATA[2012-Udsalg2-Sum]]></value><value><![CDATA[2012-UDS2-PAUT]]></value></CatalogAdcode><ImageType cvl="ImageType"><![CDATA[modelshots]]></ImageType><ResourceFileId><![CDATA[44861]]></ResourceFileId><MimeType><![CDATA[image/jpeg]]></MimeType><Season cvl="Season"><![CDATA[121]]></Season><AltTexts><AltText locale="da" /><AltText locale="de_CH" /><AltText locale="en" /><AltText locale="de" /><AltText locale="nl" /><AltText locale="sv" /></AltTexts><Filename>D:/inRiver/Publish/Production/Pics/131884142465833567_44861.jpg</Filename></Resource></Resources></Item></Items><Assortments><Assortment id="134555954350124061" order="76" /></Assortments><Resources /></Product>
