<?xml version="1.0" encoding="UTF-8"?>
<Product id="131529275637894652"><Catalogue cvl="Catalogue" /><Fitting cvl="Fitting" /><SizeGroup><![CDATA[<SizeRange name="N36-42">N36,N37,N38,N39,N40,N41,N42</SizeRange><SizeRange name="X36-42">X36,X37,X38,X39,X40,X41,X42</SizeRange><SizeRange name="XX36-42">XX36,XX37,XX38,XX39,XX40,XX41,XX42</SizeRange>]]></SizeGroup><DescriptionCatalogues><DescriptionCatalogue locale="da">Lang støvle med lynlås i siden og elastikindsats bagpå. Er højere foran. Hæl i imiteret træfinér. Tekstilfoer 100% polyester. Kan fåes med ekstra vidde. Skaftehøjde: 36 cm, skaftevidde: 38 cm, hælhøjde: 3,5 cm.</DescriptionCatalogue><DescriptionCatalogue locale="de_CH">Stiefel mit Innenreißverschluss und Elastik-Einsatz hinten. Vorne etwas höher. Absatz aus imitiertem Furnier. Textilfutter 100% Polyester. Auch mit extra Schaftweite erhältlich. Schafthöhe: 36 cm, Schaftweite: 38 cm, Absatzhöhe: 3,5 cm.</DescriptionCatalogue><DescriptionCatalogue locale="en">Long boots with zip on side and elasticated insert on back. Taller at front. Heels in imitation wood veneer. 100% polyester lining. Extra wide fitting available. Leg height: 36 cm, leg width: 38 cm, heel height: 3.5 cm.</DescriptionCatalogue><DescriptionCatalogue locale="de">Stiefel mit Innenreißverschluss und Elastik-Einsatz hinten. Vorne etwas höher. Absatz aus imitiertem Furnier. Textilfutter 100% Polyester. Auch mit extra Schaftweite erhältlich. Schafthöhe: 36 cm, Schaftweite: 38 cm, Absatzhöhe: 3,5 cm.</DescriptionCatalogue><DescriptionCatalogue locale="nl">Lange laars met ritssluiting aan de zijkant en elastiekinzet achter. Iets hogere voorkant. Hak van imitatiehoutfineer. Stoffen voering van 100% polyester. Ook verkrijgbaar met extra wijdte. Schachthoogte: 36 cm, schachtwijdte: 38 cm, hakhoogte: 3,5 cm.</DescriptionCatalogue><DescriptionCatalogue locale="sv">Lång modell med dragkedja i sidan och infälld resår bak. Högre fram. Klack av imiterat trä. Textilfoder av 100% polyester. Finns även med extra vidd. Skafthöjd: 36 cm, skaftvidd: 38 cm, klackhöjd: 3,5 cm.</DescriptionCatalogue></DescriptionCatalogues><Animal_Origin>false</Animal_Origin><MeasureHeading cvl="MeasureHeading"><value><![CDATA[Length]]></value><value><![CDATA[Size]]></value></MeasureHeading><MeasurementDescriptions><MeasurementDescription locale="da" /><MeasurementDescription locale="de_CH" /><MeasurementDescription locale="en" /><MeasurementDescription locale="de" /><MeasurementDescription locale="nl" /><MeasurementDescription locale="sv" /></MeasurementDescriptions><Program cvl="Program"><![CDATA[D]]></Program><IsLive /><Composition cvl="Composition"><![CDATA[899]]></Composition><ProductMainGroup cvl="ProductMainGroup"><![CDATA[14]]></ProductMainGroup><SizeGuide /><SizeGroupName><![CDATA[N_XX_36-42]]></SizeGroupName><MeasurementImage /><ProductStatus cvl="ProductStatus" /><translationReady /><Season cvl="Season" /><Concept cvl="Concept" /><DisplaySize>true</DisplaySize><MeasureChartAbrv><![CDATA[FWB4]]></MeasureChartAbrv><ProductSubGroup cvl="ProductSubGroup" /><LengthDescription cvl="LengthDescription"><![CDATA[MES25]]></LengthDescription><ProductGroup cvl="ProductGroup"><![CDATA[1400]]></ProductGroup><DescriptionWebs><DescriptionWeb locale="da" /><DescriptionWeb locale="de_CH" /><DescriptionWeb locale="en" /><DescriptionWeb locale="de" /><DescriptionWeb locale="nl" /><DescriptionWeb locale="sv" /></DescriptionWebs><HeaderWebs><HeaderWeb locale="da">Skindstøvle</HeaderWeb><HeaderWeb locale="de_CH">Lederstiefel</HeaderWeb><HeaderWeb locale="en">Leather boots</HeaderWeb><HeaderWeb locale="de">Lederstiefel</HeaderWeb><HeaderWeb locale="nl">Leren laars</HeaderWeb><HeaderWeb locale="sv">Skinnstövlar</HeaderWeb></HeaderWebs><CompositionFoders><CompositionFoder locale="da" /><CompositionFoder locale="de_CH" /><CompositionFoder locale="en" /><CompositionFoder locale="de" /><CompositionFoder locale="nl" /><CompositionFoder locale="sv" /></CompositionFoders><DescriptionPDMs><DescriptionPDM locale="da">Leather boot with zipper inside leg and wide elastic slit in back for regulation. 4cm high imitated veneer heel. Fleece lining - 100% polyester. 36cm heigh leg - 38cm leg circumference. Normal -XL and XXL width. Shell fabric/Yderstof/Oberstoff 80% Leather/Læder/Leder 20% Cotton/Bomuld/Baumwolle</DescriptionPDM><DescriptionPDM locale="de_CH" /><DescriptionPDM locale="en" /><DescriptionPDM locale="de" /><DescriptionPDM locale="nl" /><DescriptionPDM locale="sv" /></DescriptionPDMs><usedInSpread /><LengthImage /><DisplayComposition>true</DisplayComposition><StyleNbr><![CDATA[2874]]></StyleNbr><HeaderPDMs><HeaderPDM locale="da">Skindstøvle</HeaderPDM><HeaderPDM locale="de_CH" /><HeaderPDM locale="en" /><HeaderPDM locale="de" /><HeaderPDM locale="nl" /><HeaderPDM locale="sv" /></HeaderPDMs><Items><Item id="131529275536238232"><Descriptions><Description locale="da" /><Description locale="de_CH" /><Description locale="en" /><Description locale="de" /><Description locale="nl" /><Description locale="sv" /></Descriptions><AdCodes /><CinoNumber><![CDATA[75327]]></CinoNumber><Prices /><Portals><Portal locale="da" /><Portal locale="de_CH" /><Portal locale="en" /><Portal locale="de" /><Portal locale="nl" /><Portal locale="sv" /></Portals><WashTemperature cvl="WashIcon" /><Inspirations><Inspiration locale="da" /><Inspiration locale="de_CH" /><Inspiration locale="en" /><Inspiration locale="de" /><Inspiration locale="nl" /><Inspiration locale="sv" /></Inspirations><Color cvl="Color"><![CDATA[9000]]></Color><ProductSubGroup /><Sizess><Sizes locale="da">N36-N37-N38-N39-N40-N41-N42</Sizes><Sizes locale="de_CH">N36-N37-N38-N39-N40-N41-N42</Sizes><Sizes locale="en">N36-N37-N38-N39-N40-N41-N42</Sizes><Sizes locale="de">N36-N37-N38-N39-N40-N41-N42</Sizes><Sizes locale="nl">N36-N37-N38-N39-N40-N41-N42</Sizes><Sizes locale="sv">N36-N37-N38-N39-N40-N41-N42</Sizes></Sizess><WashIcon cvl="WashIcon" /><ColorGroup><![CDATA[Black]]></ColorGroup><MeasurementChart><![CDATA[<Measure name="Heel height" description="Heel height"><Size name="N36">3.50</Size><Size name="N37">3.50</Size><Size name="N38">3.50</Size><Size name="N39">3.50</Size><Size name="N40">3.50</Size><Size name="N41">3.50</Size><Size name="N42">3.50</Size></Measure><Measure name="Inside length" description="Inside length"><Size name="N36">24.80</Size><Size name="N37">25.50</Size><Size name="N38">26.20</Size><Size name="N39">26.90</Size><Size name="N40">27.60</Size><Size name="N41">28.20</Size><Size name="N42">28.80</Size></Measure><Measure name="Leg circumference" description="Leg circumference"><Size name="N36">35.00</Size><Size name="N37">36.00</Size><Size name="N38">37.00</Size><Size name="N39">38.00</Size><Size name="N40">38.50</Size><Size name="N41">39.00</Size><Size name="N42">39.50</Size></Measure><Measure name="Leg height" description="Leg height"><Size name="N36">36.00</Size><Size name="N37">36.00</Size><Size name="N38">36.00</Size><Size name="N39">36.00</Size><Size name="N40">36.00</Size><Size name="N41">36.00</Size><Size name="N42">36.00</Size></Measure>]]></MeasurementChart><Length><![CDATA[38.00]]></Length><ActiveCatalogue cvl="Catalogue" /><LengthChart><![CDATA[<Size name="N36">35.00</Size><Size name="N37">36.00</Size><Size name="N38">37.00</Size><Size name="N39">38.00</Size><Size name="N40">38.50</Size><Size name="N41">39.00</Size><Size name="N42">39.50</Size>]]></LengthChart><WashInstructions><WashInstruction locale="da" /><WashInstruction locale="de_CH" /><WashInstruction locale="en" /><WashInstruction locale="de" /><WashInstruction locale="nl" /><WashInstruction locale="sv" /></WashInstructions><IsLive /><Resources /></Item><Item id="13152927556447152"><Descriptions><Description locale="da" /><Description locale="de_CH" /><Description locale="en" /><Description locale="de" /><Description locale="nl" /><Description locale="sv" /></Descriptions><AdCodes /><CinoNumber><![CDATA[75328]]></CinoNumber><Prices /><Portals><Portal locale="da" /><Portal locale="de_CH" /><Portal locale="en" /><Portal locale="de" /><Portal locale="nl" /><Portal locale="sv" /></Portals><WashTemperature cvl="WashIcon" /><Inspirations><Inspiration locale="da" /><Inspiration locale="de_CH" /><Inspiration locale="en" /><Inspiration locale="de" /><Inspiration locale="nl" /><Inspiration locale="sv" /></Inspirations><Color cvl="Color"><![CDATA[9000]]></Color><ProductSubGroup /><Sizess><Sizes locale="da">X36-X37-X38-X39-X40-X41-X42</Sizes><Sizes locale="de_CH">X36-X37-X38-X39-X40-X41-X42</Sizes><Sizes locale="en">X36-X37-X38-X39-X40-X41-X42</Sizes><Sizes locale="de">X36-X37-X38-X39-X40-X41-X42</Sizes><Sizes locale="nl">X36-X37-X38-X39-X40-X41-X42</Sizes><Sizes locale="sv">X36-X37-X38-X39-X40-X41-X42</Sizes></Sizess><WashIcon cvl="WashIcon" /><ColorGroup><![CDATA[Black]]></ColorGroup><MeasurementChart><![CDATA[<Measure name="Heel height" description="Heel height"><Size name="X36">3.50</Size><Size name="X37">3.50</Size><Size name="X38">3.50</Size><Size name="X39">3.50</Size><Size name="X40">3.50</Size><Size name="X41">3.50</Size><Size name="X42">3.50</Size></Measure><Measure name="Inside length" description="Inside length"><Size name="X36">24.80</Size><Size name="X37">25.50</Size><Size name="X38">26.20</Size><Size name="X39">26.90</Size><Size name="X40">27.60</Size><Size name="X41">28.20</Size><Size name="X42">28.80</Size></Measure><Measure name="Leg circumference" description="Leg circumference"><Size name="X36">38.00</Size><Size name="X37">39.00</Size><Size name="X38">40.00</Size><Size name="X39">41.00</Size><Size name="X40">41.50</Size><Size name="X41">42.00</Size><Size name="X42">42.50</Size></Measure><Measure name="Leg height" description="Leg height"><Size name="X36">36.00</Size><Size name="X37">36.00</Size><Size name="X38">36.00</Size><Size name="X39">36.00</Size><Size name="X40">36.00</Size><Size name="X41">36.00</Size><Size name="X42">36.00</Size></Measure>]]></MeasurementChart><Length><![CDATA[41.00]]></Length><ActiveCatalogue cvl="Catalogue" /><LengthChart><![CDATA[<Size name="X36">38.00</Size><Size name="X37">39.00</Size><Size name="X38">40.00</Size><Size name="X39">41.00</Size><Size name="X40">41.50</Size><Size name="X41">42.00</Size><Size name="X42">42.50</Size>]]></LengthChart><WashInstructions><WashInstruction locale="da" /><WashInstruction locale="de_CH" /><WashInstruction locale="en" /><WashInstruction locale="de" /><WashInstruction locale="nl" /><WashInstruction locale="sv" /></WashInstructions><IsLive /><Resources /></Item><Item id="131529275598711805"><Descriptions><Description locale="da" /><Description locale="de_CH" /><Description locale="en" /><Description locale="de" /><Description locale="nl" /><Description locale="sv" /></Descriptions><AdCodes /><CinoNumber><![CDATA[75329]]></CinoNumber><Prices /><Portals><Portal locale="da" /><Portal locale="de_CH" /><Portal locale="en" /><Portal locale="de" /><Portal locale="nl" /><Portal locale="sv" /></Portals><WashTemperature cvl="WashIcon" /><Inspirations><Inspiration locale="da" /><Inspiration locale="de_CH" /><Inspiration locale="en" /><Inspiration locale="de" /><Inspiration locale="nl" /><Inspiration locale="sv" /></Inspirations><Color cvl="Color"><![CDATA[9000]]></Color><ProductSubGroup /><Sizess><Sizes locale="da">XX36-XX37-XX38-XX39-XX40-XX41-XX42</Sizes><Sizes locale="de_CH">XX36-XX37-XX38-XX39-XX40-XX41-XX42</Sizes><Sizes locale="en">XX36-XX37-XX38-XX39-XX40-XX41-XX42</Sizes><Sizes locale="de">XX36-XX37-XX38-XX39-XX40-XX41-XX42</Sizes><Sizes locale="nl">XX36-XX37-XX38-XX39-XX40-XX41-XX42</Sizes><Sizes locale="sv">XX36-XX37-XX38-XX39-XX40-XX41-XX42</Sizes></Sizess><WashIcon cvl="WashIcon" /><ColorGroup><![CDATA[Black]]></ColorGroup><MeasurementChart><![CDATA[<Measure name="Heel height" description="Heel height"><Size name="XX36">3.50</Size><Size name="XX37">3.50</Size><Size name="XX38">3.50</Size><Size name="XX39">3.50</Size><Size name="XX40">3.50</Size><Size name="XX41">3.50</Size><Size name="XX42">3.50</Size></Measure><Measure name="Inside length" description="Inside length"><Size name="XX36">24.80</Size><Size name="XX37">25.50</Size><Size name="XX38">26.20</Size><Size name="XX39">26.90</Size><Size name="XX40">27.60</Size><Size name="XX41">28.20</Size><Size name="XX42">28.80</Size></Measure><Measure name="Leg circumference" description="Leg circumference"><Size name="XX36">41.00</Size><Size name="XX37">42.00</Size><Size name="XX38">43.00</Size><Size name="XX39">44.00</Size><Size name="XX40">44.50</Size><Size name="XX41">45.00</Size><Size name="XX42">45.50</Size></Measure><Measure name="Leg height" description="Leg height"><Size name="XX36">36.00</Size><Size name="XX37">36.00</Size><Size name="XX38">36.00</Size><Size name="XX39">36.00</Size><Size name="XX40">36.00</Size><Size name="XX41">36.00</Size><Size name="XX42">36.00</Size></Measure>]]></MeasurementChart><Length><![CDATA[44.00]]></Length><ActiveCatalogue cvl="Catalogue" /><LengthChart><![CDATA[<Size name="XX36">41.00</Size><Size name="XX37">42.00</Size><Size name="XX38">43.00</Size><Size name="XX39">44.00</Size><Size name="XX40">44.50</Size><Size name="XX41">45.00</Size><Size name="XX42">45.50</Size>]]></LengthChart><WashInstructions><WashInstruction locale="da" /><WashInstruction locale="de_CH" /><WashInstruction locale="en" /><WashInstruction locale="de" /><WashInstruction locale="nl" /><WashInstruction locale="sv" /></WashInstructions><IsLive /><Resources /></Item></Items><Assortments><Assortment id="134555927777377834" order="15" /></Assortments><Resources /></Product>
