<?xml version="1.0" encoding="UTF-8"?>
<Product id="134424613939623871" action="updated"><Catalogue cvl="Catalogue"><value><![CDATA[2013-FAV-PSPR]]></value><value><![CDATA[2013-BAP-SPR]]></value><value><![CDATA[2013-BAP-PSPR]]></value><value><![CDATA[2013-PLUS-PSPR]]></value></Catalogue><Fitting cvl="Fitting"><![CDATA[Regular]]></Fitting><SizeGroup><![CDATA[<SizeRange name="34-54">34,36,38,40,42,44,46,48,50,52,54</SizeRange>]]></SizeGroup><DescriptionCatalogues><DescriptionCatalogue locale="da">Kort feminin model med overskæring forneden. Skjult hægtelukning. Let kvalitet med struktur. Foer: 100% polyester. Professionel rens.</DescriptionCatalogue><DescriptionCatalogue locale="de_CH">Kurzes, feminines Modell mit Teilungsnaht unten. Verdeckter Häkchenverschluss. Leichte Qualität mit Struktur. Futter: 100% Polyester. Professionelle Reinigung.</DescriptionCatalogue><DescriptionCatalogue locale="en">Short feminine design with overlap at hem. Concealed hook closure. Lightweight textured fabric. Lining: 100% polyester. Dry-clean only.</DescriptionCatalogue><DescriptionCatalogue locale="de">Kurzes, feminines Modell mit Teilungsnaht unten. Verdeckter Häkchenverschluss. Leichte Qualität mit Struktur. Futter: 100% Polyester. Professionelle Reinigung.</DescriptionCatalogue><DescriptionCatalogue locale="nl">Kort vrouwelijk model met dwarsnaad onderaan. Blinde haakjessluiting. Lichte kwaliteit met structuur. Voering: 100% polyester. Chemisch laten reinigen.</DescriptionCatalogue><DescriptionCatalogue locale="sv">Kort feminin modell, avskuren nertill. Dold hakknäppning. Lätt kvalitet med struktur. Foder: 100% polyester. Endast kemtvätt.</DescriptionCatalogue></DescriptionCatalogues><Animal_Origin>false</Animal_Origin><MeasureHeading cvl="MeasureHeading"><value><![CDATA[Length]]></value><value><![CDATA[Size]]></value></MeasureHeading><MeasurementDescriptions><MeasurementDescription locale="da" /><MeasurementDescription locale="de_CH" /><MeasurementDescription locale="en" /><MeasurementDescription locale="de" /><MeasurementDescription locale="nl" /><MeasurementDescription locale="sv" /></MeasurementDescriptions><Program cvl="Program"><![CDATA[D]]></Program><IsLive /><Composition cvl="Composition"><![CDATA[4]]></Composition><ProductMainGroup cvl="ProductMainGroup"><![CDATA[20]]></ProductMainGroup><SizeGuide /><SizeGroupName><![CDATA[34-54]]></SizeGroupName><MeasurementImage /><ProductStatus cvl="ProductStatus" /><translationReady /><Season cvl="Season"><value><![CDATA[131]]></value></Season><Concept cvl="Concept"><![CDATA[B]]></Concept><DisplaySize>true</DisplaySize><MeasureChartAbrv><![CDATA[M1]]></MeasureChartAbrv><ProductSubGroup cvl="ProductSubGroup" /><LengthDescription cvl="LengthDescription" /><ProductGroup cvl="ProductGroup"><![CDATA[2000]]></ProductGroup><DescriptionWebs><DescriptionWeb locale="da" /><DescriptionWeb locale="de_CH" /><DescriptionWeb locale="en" /><DescriptionWeb locale="de" /><DescriptionWeb locale="nl" /><DescriptionWeb locale="sv" /></DescriptionWebs><HeaderWebs><HeaderWeb locale="da">Blazer</HeaderWeb><HeaderWeb locale="de_CH">Blazer</HeaderWeb><HeaderWeb locale="en">Blazer</HeaderWeb><HeaderWeb locale="de">Blazer</HeaderWeb><HeaderWeb locale="nl">Blazer</HeaderWeb><HeaderWeb locale="sv">Blazer</HeaderWeb></HeaderWebs><CompositionFoders><CompositionFoder locale="da" /><CompositionFoder locale="de_CH" /><CompositionFoder locale="en" /><CompositionFoder locale="de" /><CompositionFoder locale="nl" /><CompositionFoder locale="sv" /></CompositionFoders><DescriptionPDMs><DescriptionPDM locale="da">SGR: Blazer Shell fabric/Yderstof/Oberstoff 100% Cotton/Bomuld/Baumwolle Lining/Foer/Futter 100% Polyester Professionel rens</DescriptionPDM><DescriptionPDM locale="de_CH" /><DescriptionPDM locale="en" /><DescriptionPDM locale="de" /><DescriptionPDM locale="nl" /><DescriptionPDM locale="sv" /></DescriptionPDMs><usedInSpread /><LengthImage /><DisplayComposition>true</DisplayComposition><StyleNbr><![CDATA[7006]]></StyleNbr><HeaderPDMs><HeaderPDM locale="da">Blazer</HeaderPDM><HeaderPDM locale="de_CH" /><HeaderPDM locale="en" /><HeaderPDM locale="de" /><HeaderPDM locale="nl" /><HeaderPDM locale="sv" /></HeaderPDMs><Items><Item id="134512428242521320"><Descriptions><Description locale="da" /><Description locale="de_CH" /><Description locale="en" /><Description locale="de" /><Description locale="nl" /><Description locale="sv" /></Descriptions><AdCodes><![CDATA[<AdCode catalogue="2013-FAV-PSPR">F</AdCode><AdCode catalogue="2013-BAP-SPR">M</AdCode><AdCode catalogue="2013-BAP-PSPR">1</AdCode><AdCode catalogue="2013-PLUS-PSPR">Z</AdCode>]]></AdCodes><CinoNumber><![CDATA[78213]]></CinoNumber><Prices><![CDATA[<Catalogue name="2013-FAV-PSPR"><Country code="DK" currency="DKK"><Size name="34">579.95</Size><Size name="36">579.95</Size><Size name="38">579.95</Size><Size name="40">579.95</Size><Size name="42">579.95</Size><Size name="44">579.95</Size><Size name="46">579.95</Size><Size name="48">579.95</Size><Size name="50">579.95</Size><Size name="52">579.95</Size><Size name="54">579.95</Size></Country><Country code="SE" currency="SEK"><Size name="34">729.95</Size><Size name="36">729.95</Size><Size name="38">729.95</Size><Size name="40">729.95</Size><Size name="42">729.95</Size><Size name="44">729.95</Size><Size name="46">729.95</Size><Size name="48">729.95</Size><Size name="50">729.95</Size><Size name="52">729.95</Size><Size name="54">729.95</Size></Country><Country code="NL" currency="EUR"><Size name="34">84.95</Size><Size name="36">84.95</Size><Size name="38">84.95</Size><Size name="40">84.95</Size><Size name="42">84.95</Size><Size name="44">84.95</Size><Size name="46">84.95</Size><Size name="48">84.95</Size><Size name="50">84.95</Size><Size name="52">84.95</Size><Size name="54">84.95</Size></Country><Country code="DE" currency="EUR"><Size name="34">89.95</Size><Size name="36">89.95</Size><Size name="38">89.95</Size><Size name="40">89.95</Size><Size name="42">89.95</Size><Size name="44">89.95</Size><Size name="46">89.95</Size><Size name="48">89.95</Size><Size name="50">89.95</Size><Size name="52">89.95</Size><Size name="54">89.95</Size></Country><Country code="CH" currency="SFR"><Size name="34">169.95</Size><Size name="36">169.95</Size><Size name="38">169.95</Size><Size name="40">169.95</Size><Size name="42">169.95</Size><Size name="44">169.95</Size><Size name="46">169.95</Size><Size name="48">169.95</Size><Size name="50">169.95</Size><Size name="52">169.95</Size><Size name="54">169.95</Size></Country><Country code="GB" currency="GBP"><Size name="8">73.00</Size><Size name="10">73.00</Size><Size name="12">73.00</Size><Size name="14">73.00</Size><Size name="16">73.00</Size><Size name="18">73.00</Size><Size name="20">73.00</Size><Size name="22">73.00</Size><Size name="24">73.00</Size><Size name="26">73.00</Size><Size name="28">73.00</Size></Country></Catalogue><Catalogue name="2013-BAP-SPR"><Country code="DK" currency="DKK"><Size name="34">579.95</Size><Size name="36">579.95</Size><Size name="38">579.95</Size><Size name="40">579.95</Size><Size name="42">579.95</Size><Size name="44">579.95</Size><Size name="46">579.95</Size><Size name="48">579.95</Size><Size name="50">579.95</Size><Size name="52">579.95</Size><Size name="54">579.95</Size></Country><Country code="SE" currency="SEK"><Size name="34">729.95</Size><Size name="36">729.95</Size><Size name="38">729.95</Size><Size name="40">729.95</Size><Size name="42">729.95</Size><Size name="44">729.95</Size><Size name="46">729.95</Size><Size name="48">729.95</Size><Size name="50">729.95</Size><Size name="52">729.95</Size><Size name="54">729.95</Size></Country><Country code="NL" currency="EUR"><Size name="34">84.95</Size><Size name="36">84.95</Size><Size name="38">84.95</Size><Size name="40">84.95</Size><Size name="42">84.95</Size><Size name="44">84.95</Size><Size name="46">84.95</Size><Size name="48">84.95</Size><Size name="50">84.95</Size><Size name="52">84.95</Size><Size name="54">84.95</Size></Country><Country code="DE" currency="EUR"><Size name="34">89.95</Size><Size name="36">89.95</Size><Size name="38">89.95</Size><Size name="40">89.95</Size><Size name="42">89.95</Size><Size name="44">89.95</Size><Size name="46">89.95</Size><Size name="48">89.95</Size><Size name="50">89.95</Size><Size name="52">89.95</Size><Size name="54">89.95</Size></Country><Country code="CH" currency="SFR"><Size name="34">169.95</Size><Size name="36">169.95</Size><Size name="38">169.95</Size><Size name="40">169.95</Size><Size name="42">169.95</Size><Size name="44">169.95</Size><Size name="46">169.95</Size><Size name="48">169.95</Size><Size name="50">169.95</Size><Size name="52">169.95</Size><Size name="54">169.95</Size></Country><Country code="GB" currency="GBP"><Size name="8">73.00</Size><Size name="10">73.00</Size><Size name="12">73.00</Size><Size name="14">73.00</Size><Size name="16">73.00</Size><Size name="18">73.00</Size><Size name="20">73.00</Size><Size name="22">73.00</Size><Size name="24">73.00</Size><Size name="26">73.00</Size><Size name="28">73.00</Size></Country></Catalogue><Catalogue name="2013-BAP-PSPR"><Country code="DK" currency="DKK"><Size name="34">579.95</Size><Size name="36">579.95</Size><Size name="38">579.95</Size><Size name="40">579.95</Size><Size name="42">579.95</Size><Size name="44">579.95</Size><Size name="46">579.95</Size><Size name="48">579.95</Size><Size name="50">579.95</Size><Size name="52">579.95</Size><Size name="54">579.95</Size></Country><Country code="SE" currency="SEK"><Size name="34">729.95</Size><Size name="36">729.95</Size><Size name="38">729.95</Size><Size name="40">729.95</Size><Size name="42">729.95</Size><Size name="44">729.95</Size><Size name="46">729.95</Size><Size name="48">729.95</Size><Size name="50">729.95</Size><Size name="52">729.95</Size><Size name="54">729.95</Size></Country><Country code="NL" currency="EUR"><Size name="34">84.95</Size><Size name="36">84.95</Size><Size name="38">84.95</Size><Size name="40">84.95</Size><Size name="42">84.95</Size><Size name="44">84.95</Size><Size name="46">84.95</Size><Size name="48">84.95</Size><Size name="50">84.95</Size><Size name="52">84.95</Size><Size name="54">84.95</Size></Country><Country code="DE" currency="EUR"><Size name="34">89.95</Size><Size name="36">89.95</Size><Size name="38">89.95</Size><Size name="40">89.95</Size><Size name="42">89.95</Size><Size name="44">89.95</Size><Size name="46">89.95</Size><Size name="48">89.95</Size><Size name="50">89.95</Size><Size name="52">89.95</Size><Size name="54">89.95</Size></Country><Country code="CH" currency="SFR"><Size name="34">169.95</Size><Size name="36">169.95</Size><Size name="38">169.95</Size><Size name="40">169.95</Size><Size name="42">169.95</Size><Size name="44">169.95</Size><Size name="46">169.95</Size><Size name="48">169.95</Size><Size name="50">169.95</Size><Size name="52">169.95</Size><Size name="54">169.95</Size></Country><Country code="GB" currency="GBP"><Size name="8">73.00</Size><Size name="10">73.00</Size><Size name="12">73.00</Size><Size name="14">73.00</Size><Size name="16">73.00</Size><Size name="18">73.00</Size><Size name="20">73.00</Size><Size name="22">73.00</Size><Size name="24">73.00</Size><Size name="26">73.00</Size><Size name="28">73.00</Size></Country></Catalogue><Catalogue name="2013-PLUS-PSPR"><Country code="DK" currency="DKK"><Size name="34">579.95</Size><Size name="36">579.95</Size><Size name="38">579.95</Size><Size name="40">579.95</Size><Size name="42">579.95</Size><Size name="44">579.95</Size><Size name="46">579.95</Size><Size name="48">579.95</Size><Size name="50">579.95</Size><Size name="52">579.95</Size><Size name="54">579.95</Size></Country><Country code="SE" currency="SEK"><Size name="34">729.95</Size><Size name="36">729.95</Size><Size name="38">729.95</Size><Size name="40">729.95</Size><Size name="42">729.95</Size><Size name="44">729.95</Size><Size name="46">729.95</Size><Size name="48">729.95</Size><Size name="50">729.95</Size><Size name="52">729.95</Size><Size name="54">729.95</Size></Country><Country code="NL" currency="EUR"><Size name="34">84.95</Size><Size name="36">84.95</Size><Size name="38">84.95</Size><Size name="40">84.95</Size><Size name="42">84.95</Size><Size name="44">84.95</Size><Size name="46">84.95</Size><Size name="48">84.95</Size><Size name="50">84.95</Size><Size name="52">84.95</Size><Size name="54">84.95</Size></Country><Country code="DE" currency="EUR"><Size name="34">89.95</Size><Size name="36">89.95</Size><Size name="38">89.95</Size><Size name="40">89.95</Size><Size name="42">89.95</Size><Size name="44">89.95</Size><Size name="46">89.95</Size><Size name="48">89.95</Size><Size name="50">89.95</Size><Size name="52">89.95</Size><Size name="54">89.95</Size></Country><Country code="CH" currency="SFR"><Size name="34">169.95</Size><Size name="36">169.95</Size><Size name="38">169.95</Size><Size name="40">169.95</Size><Size name="42">169.95</Size><Size name="44">169.95</Size><Size name="46">169.95</Size><Size name="48">169.95</Size><Size name="50">169.95</Size><Size name="52">169.95</Size><Size name="54">169.95</Size></Country><Country code="GB" currency="GBP"><Size name="8">73.00</Size><Size name="10">73.00</Size><Size name="12">73.00</Size><Size name="14">73.00</Size><Size name="16">73.00</Size><Size name="18">73.00</Size><Size name="20">73.00</Size><Size name="22">73.00</Size><Size name="24">73.00</Size><Size name="26">73.00</Size><Size name="28">73.00</Size></Country></Catalogue>]]></Prices><Portals><Portal locale="da" /><Portal locale="de_CH" /><Portal locale="en" /><Portal locale="de" /><Portal locale="nl" /><Portal locale="sv" /></Portals><WashTemperature cvl="WashIcon" /><Inspirations><Inspiration locale="da" /><Inspiration locale="de_CH" /><Inspiration locale="en" /><Inspiration locale="de" /><Inspiration locale="nl" /><Inspiration locale="sv" /></Inspirations><Color cvl="Color"><![CDATA[1005]]></Color><ProductSubGroup /><Sizess><Sizes locale="da">34-36-38-40-42-44-46-48-50-52-54</Sizes><Sizes locale="de_CH">34-36-38-40-42-44-46-48-50-52-54</Sizes><Sizes locale="en">8-10-12-14-16-18-20-22-24-26-28</Sizes><Sizes locale="de">34-36-38-40-42-44-46-48-50-52-54</Sizes><Sizes locale="nl">34-36-38-40-42-44-46-48-50-52-54</Sizes><Sizes locale="sv">34-36-38-40-42-44-46-48-50-52-54</Sizes></Sizess><WashIcon cvl="WashIcon"><value><![CDATA[10100]]></value><value><![CDATA[20100]]></value><value><![CDATA[50100]]></value><value><![CDATA[30300]]></value><value><![CDATA[40500]]></value></WashIcon><ColorGroup><![CDATA[Sand]]></ColorGroup><MeasurementChart><![CDATA[<Measure name="1/2 Chest/ bust width, 2 cm below" description="1/2 Chest/ bust width, 2 cm below"><Size name="34">46.00</Size><Size name="36">47.50</Size><Size name="38">49.00</Size><Size name="40">51.00</Size><Size name="42">53.00</Size><Size name="44">55.50</Size><Size name="46">58.50</Size><Size name="48">61.50</Size><Size name="50">64.50</Size><Size name="52">67.50</Size><Size name="54">70.50</Size></Measure><Measure name="Ba. length, neckh. tip to waistb." description="Ba. length, neckh. tip to waistb."><Size name="34">41.60</Size><Size name="36">42.30</Size><Size name="38">43.00</Size><Size name="40">43.70</Size><Size name="42">44.40</Size><Size name="44">45.10</Size><Size name="46">45.80</Size><Size name="48">46.50</Size><Size name="50">47.20</Size><Size name="52">47.90</Size><Size name="54">48.90</Size></Measure><Measure name="1/2 Waist/-band width" description="1/2 Waist/-band width"><Size name="34">41.00</Size><Size name="36">42.50</Size><Size name="38">44.00</Size><Size name="40">46.00</Size><Size name="42">48.50</Size><Size name="44">51.50</Size><Size name="46">54.50</Size><Size name="48">57.50</Size><Size name="50">61.00</Size><Size name="52">64.50</Size><Size name="54">68.00</Size></Measure><Measure name="1/2 Hem width" description="1/2 Hem width"><Size name="34">50.00</Size><Size name="36">51.50</Size><Size name="38">53.00</Size><Size name="40">55.00</Size><Size name="42">57.00</Size><Size name="44">59.75</Size><Size name="46">62.50</Size><Size name="48">65.25</Size><Size name="50">68.00</Size><Size name="52">70.75</Size><Size name="54">73.75</Size></Measure><Measure name="Should. width" description="Should. width"><Size name="34">37.50</Size><Size name="36">38.25</Size><Size name="38">39.00</Size><Size name="40">40.00</Size><Size name="42">41.00</Size><Size name="44">42.00</Size><Size name="46">43.20</Size><Size name="48">44.40</Size><Size name="50">45.60</Size><Size name="52">46.80</Size><Size name="54">48.00</Size></Measure><Measure name="Back breadth height" description="Back breadth height"><Size name="34">15.60</Size><Size name="36">15.80</Size><Size name="38">16.00</Size><Size name="40">16.20</Size><Size name="42">16.40</Size><Size name="44">16.90</Size><Size name="46">17.40</Size><Size name="48">17.90</Size><Size name="50">18.40</Size><Size name="52">18.90</Size><Size name="54">19.60</Size></Measure><Measure name="Back breadth" description="Back breadth"><Size name="34">36.50</Size><Size name="36">37.25</Size><Size name="38">38.00</Size><Size name="40">39.00</Size><Size name="42">40.00</Size><Size name="44">41.00</Size><Size name="46">42.30</Size><Size name="48">43.60</Size><Size name="50">44.90</Size><Size name="52">46.20</Size><Size name="54">47.50</Size></Measure><Measure name="Front breadth height" description="Front breadth height"><Size name="34">15.60</Size><Size name="36">15.80</Size><Size name="38">16.00</Size><Size name="40">16.20</Size><Size name="42">16.40</Size><Size name="44">16.90</Size><Size name="46">17.40</Size><Size name="48">17.90</Size><Size name="50">18.40</Size><Size name="52">18.90</Size><Size name="54">19.60</Size></Measure><Measure name="Front breadth" description="Front breadth"><Size name="34">34.50</Size><Size name="36">35.25</Size><Size name="38">36.00</Size><Size name="40">37.00</Size><Size name="42">38.00</Size><Size name="44">39.00</Size><Size name="46">40.20</Size><Size name="48">41.40</Size><Size name="50">42.60</Size><Size name="52">43.80</Size><Size name="54">45.00</Size></Measure><Measure name="Armhole depth, verti. fr. neckh. tip" description="Armhole depth, verti. fr. neckh. tip"><Size name="34">24.00</Size><Size name="36">24.50</Size><Size name="38">25.00</Size><Size name="40">25.50</Size><Size name="42">26.00</Size><Size name="44">26.50</Size><Size name="46">27.25</Size><Size name="48">28.00</Size><Size name="50">28.75</Size><Size name="52">29.50</Size><Size name="54">30.25</Size></Measure><Measure name="Sleeve length" description="Sleeve length"><Size name="34">63.30</Size><Size name="36">64.00</Size><Size name="38">63.50</Size><Size name="40">64.00</Size><Size name="42">63.50</Size><Size name="44">64.00</Size><Size name="46">63.40</Size><Size name="48">62.80</Size><Size name="50">63.20</Size><Size name="52">62.60</Size><Size name="54">62.00</Size></Measure><Measure name="1/2 Upper arm width" description="1/2 Upper arm width"><Size name="34">16.80</Size><Size name="36">17.40</Size><Size name="38">18.00</Size><Size name="40">18.60</Size><Size name="42">19.20</Size><Size name="44">20.10</Size><Size name="46">21.00</Size><Size name="48">21.90</Size><Size name="50">22.80</Size><Size name="52">23.70</Size><Size name="54">24.60</Size></Measure><Measure name="Sleeve length to elbow width Inseam" description="Sleeve length to elbow width Inseam"><Size name="34">23.90</Size><Size name="36">24.25</Size><Size name="38">24.00</Size><Size name="40">24.25</Size><Size name="42">24.00</Size><Size name="44">24.25</Size><Size name="46">23.95</Size><Size name="48">23.65</Size><Size name="50">23.85</Size><Size name="52">23.55</Size><Size name="54">23.25</Size></Measure><Measure name="1/2 Elbow width" description="1/2 Elbow width"><Size name="34">14.70</Size><Size name="36">15.10</Size><Size name="38">15.50</Size><Size name="40">15.90</Size><Size name="42">16.30</Size><Size name="44">17.05</Size><Size name="46">17.80</Size><Size name="48">18.55</Size><Size name="50">19.30</Size><Size name="52">20.05</Size><Size name="54">20.80</Size></Measure><Measure name="1/2 Width of sl. hem" description="1/2 Width of sl. hem"><Size name="34">12.10</Size><Size name="36">12.30</Size><Size name="38">12.50</Size><Size name="40">12.70</Size><Size name="42">12.90</Size><Size name="44">13.30</Size><Size name="46">13.70</Size><Size name="48">14.10</Size><Size name="50">14.50</Size><Size name="52">14.90</Size><Size name="54">15.30</Size></Measure><Measure name="Neckh. breadth" description="Neckh. breadth"><Size name="34">16.20</Size><Size name="36">16.60</Size><Size name="38">17.00</Size><Size name="40">17.40</Size><Size name="42">17.80</Size><Size name="44">18.30</Size><Size name="46">18.80</Size><Size name="48">19.30</Size><Size name="50">19.80</Size><Size name="52">20.30</Size><Size name="54">20.80</Size></Measure><Measure name="Neckh. depth fr.p." description="Neckh. depth fr.p."><Size name="34">41.60</Size><Size name="36">42.30</Size><Size name="38">43.00</Size><Size name="40">43.70</Size><Size name="42">44.40</Size><Size name="44">45.10</Size><Size name="46">45.80</Size><Size name="48">46.50</Size><Size name="50">47.20</Size><Size name="52">47.90</Size><Size name="54">48.90</Size></Measure><Measure name="Neckh. depth, ba.p fr. neckh. tip" description="Neckh. depth, ba.p fr. neckh. tip"><Size name="34">1.50</Size><Size name="36">1.50</Size><Size name="38">1.50</Size><Size name="40">1.50</Size><Size name="42">1.50</Size><Size name="44">1.50</Size><Size name="46">1.50</Size><Size name="48">1.50</Size><Size name="50">1.50</Size><Size name="52">1.50</Size><Size name="54">1.50</Size></Measure><Measure name="Length fr. neckh. tip" description="Length fr. neckh. tip"><Size name="34">53.00</Size><Size name="36">54.00</Size><Size name="38">55.00</Size><Size name="40">56.00</Size><Size name="42">57.00</Size><Size name="44">58.00</Size><Size name="46">59.00</Size><Size name="48">60.00</Size><Size name="50">61.00</Size><Size name="52">62.00</Size><Size name="54">63.00</Size></Measure><Measure name="Collar height" description="Collar height"><Size name="34">4.00</Size><Size name="36">4.00</Size><Size name="38">4.00</Size><Size name="40">4.00</Size><Size name="42">4.00</Size><Size name="44">4.00</Size><Size name="46">4.00</Size><Size name="48">4.00</Size><Size name="50">4.00</Size><Size name="52">4.00</Size><Size name="54">4.00</Size></Measure><Measure name="Neckhole tip to dart" description="Neckhole tip to dart"><Size name="34">29.60</Size><Size name="36">30.30</Size><Size name="38">31.00</Size><Size name="40">31.70</Size><Size name="42">32.40</Size><Size name="44">33.10</Size><Size name="46">33.80</Size><Size name="48">34.50</Size><Size name="50">35.20</Size><Size name="52">35.90</Size><Size name="54">36.90</Size></Measure>]]></MeasurementChart><Length><![CDATA[55.00]]></Length><ActiveCatalogue cvl="Catalogue"><value><![CDATA[2013-FAV-PSPR]]></value><value><![CDATA[2013-BAP-SPR]]></value><value><![CDATA[2013-BAP-PSPR]]></value><value><![CDATA[2013-PLUS-PSPR]]></value></ActiveCatalogue><LengthChart><![CDATA[<Size name="34">53.00</Size><Size name="36">54.00</Size><Size name="38">55.00</Size><Size name="40">56.00</Size><Size name="42">57.00</Size><Size name="44">58.00</Size><Size name="46">59.00</Size><Size name="48">60.00</Size><Size name="50">61.00</Size><Size name="52">62.00</Size><Size name="54">63.00</Size>]]></LengthChart><WashInstructions><WashInstruction locale="da">Kun professionel rens.</WashInstruction><WashInstruction locale="de_CH">Nur fachmännisch Reinigung</WashInstruction><WashInstruction locale="en">Dry clean by specialist only.</WashInstruction><WashInstruction locale="de">Nur fachmännisch Reinigung.</WashInstruction><WashInstruction locale="nl">Alleen professioneel laten reinigen.</WashInstruction><WashInstruction locale="sv">Enbart professionell kemtvätt.</WashInstruction></WashInstructions><IsLive /><LeadPicture><Resource id="134666449082094481_59309" /></LeadPicture><Resources><Resource id="134752799247163850_56765"><Year cvl="Year"><![CDATA[13]]></Year><PDMIdentifier /><CatalogAdcode cvl="CatalogAdcode"><value><![CDATA[2013-BAP-SPR]]></value></CatalogAdcode><ImageType cvl="ImageType"><![CDATA[modelshots]]></ImageType><ResourceFileId><![CDATA[56765]]></ResourceFileId><MimeType><![CDATA[image/jpeg]]></MimeType><Season cvl="Season"><![CDATA[131]]></Season><AltTexts><AltText locale="da" /><AltText locale="de_CH" /><AltText locale="en" /><AltText locale="de" /><AltText locale="nl" /><AltText locale="sv" /></AltTexts><Filename>D:/inRiver/Publish/Production/Pics/134752799247163850_56765.jpg</Filename></Resource><Resource id="13475280029395148_56075"><Year cvl="Year"><![CDATA[13]]></Year><PDMIdentifier /><CatalogAdcode cvl="CatalogAdcode" /><ImageType cvl="ImageType"><![CDATA[modelshots]]></ImageType><ResourceFileId><![CDATA[56075]]></ResourceFileId><MimeType><![CDATA[image/jpeg]]></MimeType><Season cvl="Season"><![CDATA[131]]></Season><AltTexts><AltText locale="da" /><AltText locale="de_CH" /><AltText locale="en" /><AltText locale="de" /><AltText locale="nl" /><AltText locale="sv" /></AltTexts><Filename>D:/inRiver/Publish/Production/Pics/13475280029395148_56075.jpg</Filename></Resource><Resource id="134666449082094481_59309"><Year cvl="Year"><![CDATA[13]]></Year><PDMIdentifier /><CatalogAdcode cvl="CatalogAdcode"><value><![CDATA[2013-BAP-PAUT]]></value><value><![CDATA[2013-BAP-PSPR]]></value><value><![CDATA[2013-PLUS-PSPR]]></value><value><![CDATA[2013-FAV-PSPR]]></value><value><![CDATA[2013-BAP-SPR]]></value><value><![CDATA[2013-FAV2-SUM]]></value></CatalogAdcode><ImageType cvl="ImageType"><![CDATA[packshots]]></ImageType><ResourceFileId><![CDATA[59309]]></ResourceFileId><MimeType><![CDATA[image/jpeg]]></MimeType><Season cvl="Season"><![CDATA[131]]></Season><AltTexts><AltText locale="da" /><AltText locale="de_CH" /><AltText locale="en" /><AltText locale="de" /><AltText locale="nl" /><AltText locale="sv" /></AltTexts><Filename>D:/inRiver/Publish/Production/Pics/134666449082094481_59309.jpg</Filename></Resource><Resource id="13481235266248518_56752"><Year cvl="Year"><![CDATA[13]]></Year><PDMIdentifier /><CatalogAdcode cvl="CatalogAdcode"><value><![CDATA[2013-BAP-PSPR]]></value><value><![CDATA[2013-FAV-PSPR]]></value><value><![CDATA[2013-BAP-SPR]]></value></CatalogAdcode><ImageType cvl="ImageType"><![CDATA[modelshots]]></ImageType><ResourceFileId><![CDATA[56752]]></ResourceFileId><MimeType><![CDATA[image/jpeg]]></MimeType><Season cvl="Season"><![CDATA[131]]></Season><AltTexts><AltText locale="da" /><AltText locale="de_CH" /><AltText locale="en" /><AltText locale="de" /><AltText locale="nl" /><AltText locale="sv" /></AltTexts><Filename>D:/inRiver/Publish/Production/Pics/13481235266248518_56752.jpg</Filename></Resource></Resources></Item></Items><Assortments><Assortment id="134555887287782388" order="5" /><Assortment id="134555893043882595" order="5" /></Assortments><Resources><Resource id="134666449082094481_59309"><Year cvl="Year"><![CDATA[13]]></Year><PDMIdentifier /><CatalogAdcode cvl="CatalogAdcode"><value><![CDATA[2013-BAP-PAUT]]></value><value><![CDATA[2013-BAP-PSPR]]></value><value><![CDATA[2013-PLUS-PSPR]]></value><value><![CDATA[2013-FAV-PSPR]]></value><value><![CDATA[2013-BAP-SPR]]></value><value><![CDATA[2013-FAV2-SUM]]></value></CatalogAdcode><ImageType cvl="ImageType"><![CDATA[packshots]]></ImageType><ResourceFileId><![CDATA[59309]]></ResourceFileId><MimeType><![CDATA[image/jpeg]]></MimeType><Season cvl="Season"><![CDATA[131]]></Season><AltTexts><AltText locale="da" /><AltText locale="de_CH" /><AltText locale="en" /><AltText locale="de" /><AltText locale="nl" /><AltText locale="sv" /></AltTexts><Filename>D:/inRiver/Publish/Production/Pics/134666449082094481_59309.jpg</Filename></Resource></Resources></Product>
