<?xml version="1.0" encoding="UTF-8"?>
<Product id="129924235789866975" action="updated"><Catalogue cvl="Catalogue"><value><![CDATA[2012-OUTLET-WIN]]></value></Catalogue><Fitting cvl="Fitting"><![CDATA[Regular]]></Fitting><SizeGroup><![CDATA[<SizeRange name="NS-3XL">NS,NM,NL,NXL,N2XL,N3XL</SizeRange><SizeRange name="LS-3XL">LS,LM,LL,LXL,L2XL,L3XL</SizeRange>]]></SizeGroup><DescriptionCatalogues><DescriptionCatalogue locale="da">Med elastik og blonde-bindebånd i taljen. Sidelommer. Blød velourkvalitet med struktur.</DescriptionCatalogue><DescriptionCatalogue locale="de_CH">Mit Gummizug und Spitzen-Bindeband in der Taille. Seitentaschen. Weiche Velours-Qualität mit Struktur.</DescriptionCatalogue><DescriptionCatalogue locale="en">Elasticated waist with lace tie cord. Side pockets. Soft textured velour quality.</DescriptionCatalogue><DescriptionCatalogue locale="de">Mit Gummizug und Spitzen-Bindeband in der Taille. Seitentaschen. Weiche Velours-Qualität mit Struktur.</DescriptionCatalogue><DescriptionCatalogue locale="nl">Broek met elastiek en kanten koord in de taille. Zijzakken. Velourse kwaliteit met structuur.</DescriptionCatalogue><DescriptionCatalogue locale="sv">Med resår och spetsknytband i midjan. Sidofickor. Mjuk velourkvalitet med struktur.</DescriptionCatalogue></DescriptionCatalogues><Animal_Origin>false</Animal_Origin><MeasureHeading cvl="MeasureHeading"><value><![CDATA[Length]]></value><value><![CDATA[Size]]></value></MeasureHeading><MeasurementDescriptions><MeasurementDescription locale="da" /><MeasurementDescription locale="de_CH" /><MeasurementDescription locale="en" /><MeasurementDescription locale="de" /><MeasurementDescription locale="nl" /><MeasurementDescription locale="sv" /></MeasurementDescriptions><Program cvl="Program"><![CDATA[O]]></Program><IsLive /><Composition cvl="Composition"><![CDATA[330]]></Composition><ProductMainGroup cvl="ProductMainGroup"><![CDATA[44]]></ProductMainGroup><SizeGuide /><SizeGroupName><![CDATA[N_L_S-3XL]]></SizeGroupName><MeasurementImage /><ProductStatus cvl="ProductStatus" /><translationReady /><Season cvl="Season"><value><![CDATA[122]]></value></Season><Concept cvl="Concept"><![CDATA[S]]></Concept><DisplaySize>true</DisplaySize><MeasureChartAbrv><![CDATA[S]]></MeasureChartAbrv><ProductSubGroup cvl="ProductSubGroup" /><LengthDescription cvl="LengthDescription"><![CDATA[MES10]]></LengthDescription><ProductGroup cvl="ProductGroup"><![CDATA[4402]]></ProductGroup><DescriptionWebs><DescriptionWeb locale="da" /><DescriptionWeb locale="de_CH" /><DescriptionWeb locale="en" /><DescriptionWeb locale="de" /><DescriptionWeb locale="nl" /><DescriptionWeb locale="sv" /></DescriptionWebs><HeaderWebs><HeaderWeb locale="da">Homewear buks</HeaderWeb><HeaderWeb locale="de_CH">Homewear-Hose</HeaderWeb><HeaderWeb locale="en">Loungewear trousers</HeaderWeb><HeaderWeb locale="de">Homewear-Hose</HeaderWeb><HeaderWeb locale="nl">Homewear broek</HeaderWeb><HeaderWeb locale="sv">Homewear byxor</HeaderWeb></HeaderWebs><CompositionFoders><CompositionFoder locale="da" /><CompositionFoder locale="de_CH" /><CompositionFoder locale="en" /><CompositionFoder locale="de" /><CompositionFoder locale="nl" /><CompositionFoder locale="sv" /></CompositionFoders><DescriptionPDMs><DescriptionPDM locale="da">Range MMM. HW pants in velvet Shell fabric/Yderstof/Oberstoff 80% Cotton/Bomuld/Baumwolle 20% Polyester Vask 40°</DescriptionPDM><DescriptionPDM locale="de_CH" /><DescriptionPDM locale="en" /><DescriptionPDM locale="de" /><DescriptionPDM locale="nl" /><DescriptionPDM locale="sv" /></DescriptionPDMs><usedInSpread /><LengthImage /><DisplayComposition>true</DisplayComposition><StyleNbr><![CDATA[4473]]></StyleNbr><HeaderPDMs><HeaderPDM locale="da">Homewear buks</HeaderPDM><HeaderPDM locale="de_CH" /><HeaderPDM locale="en" /><HeaderPDM locale="de" /><HeaderPDM locale="nl" /><HeaderPDM locale="sv" /></HeaderPDMs><Items><Item id="130254569255281009"><Descriptions><Description locale="da" /><Description locale="de_CH" /><Description locale="en" /><Description locale="de" /><Description locale="nl" /><Description locale="sv" /></Descriptions><AdCodes><![CDATA[<AdCode catalogue="2012-OUTLET-WIN">O</AdCode>]]></AdCodes><CinoNumber><![CDATA[11403]]></CinoNumber><Prices><![CDATA[<Catalogue name="2012-OUTLET-WIN"><Country code="DK" currency="DKK"><Size name="NS">0.01</Size><Size name="NM">0.01</Size><Size name="NXL">0.01</Size><Size name="N2XL">0.01</Size><Size name="N3XL">0.01</Size></Country><Country code="SE" currency="SEK"><Size name="NS">0.01</Size><Size name="NM">0.01</Size><Size name="NXL">0.01</Size><Size name="N2XL">0.01</Size><Size name="N3XL">0.01</Size></Country><Country code="NL" currency="EUR"><Size name="NS">0.01</Size><Size name="NM">0.01</Size><Size name="NXL">0.01</Size><Size name="N2XL">0.01</Size><Size name="N3XL">0.01</Size></Country><Country code="DE" currency="EUR"><Size name="NS">0.01</Size><Size name="NM">0.01</Size><Size name="NXL">0.01</Size><Size name="N2XL">0.01</Size><Size name="N3XL">0.01</Size></Country><Country code="CH" currency="SFR"><Size name="NS">0.01</Size><Size name="NM">0.01</Size><Size name="NXL">0.01</Size><Size name="N2XL">0.01</Size><Size name="N3XL">0.01</Size></Country><Country code="GB" currency="GBP"><Size name="S">0.01</Size><Size name="M">0.01</Size><Size name="NXL">0.01</Size><Size name="N2XL">0.01</Size><Size name="N3XL">0.01</Size></Country></Catalogue>]]></Prices><Portals><Portal locale="da" /><Portal locale="de_CH" /><Portal locale="en" /><Portal locale="de" /><Portal locale="nl" /><Portal locale="sv" /></Portals><WashTemperature cvl="WashIcon" /><Inspirations><Inspiration locale="da" /><Inspiration locale="de_CH" /><Inspiration locale="en" /><Inspiration locale="de" /><Inspiration locale="nl" /><Inspiration locale="sv" /></Inspirations><Color cvl="Color"><![CDATA[6015]]></Color><ProductSubGroup /><Sizess><Sizes locale="da">NS-NM-NL-NXL-N2XL-N3XL</Sizes><Sizes locale="de_CH">NS-NM-NL-NXL-N2XL-N3XL</Sizes><Sizes locale="en">NS-NM-NL-NXL-N2XL-N3XL</Sizes><Sizes locale="de">NS-NM-NL-NXL-N2XL-N3XL</Sizes><Sizes locale="nl">NS-NM-NL-NXL-N2XL-N3XL</Sizes><Sizes locale="sv">NS-NM-NL-NXL-N2XL-N3XL</Sizes></Sizess><WashIcon cvl="WashIcon"><value><![CDATA[10700]]></value><value><![CDATA[20100]]></value><value><![CDATA[50100]]></value><value><![CDATA[30200]]></value><value><![CDATA[40500]]></value></WashIcon><ColorGroup><![CDATA[Purple]]></ColorGroup><MeasurementChart><![CDATA[<Measure name="1/2 Waist/-band width" description="1/2 Waist/-band width"><Size name="NS">35.00</Size><Size name="NM">38.00</Size><Size name="NL">42.50</Size><Size name="NXL">48.50</Size><Size name="N2XL">54.50</Size><Size name="N3XL">61.50</Size></Measure><Measure name="1/2 Waist/-band width, stret." description="1/2 Waist/-band width, stret."><Size name="NS">47.00</Size><Size name="NM">50.00</Size><Size name="NL">54.50</Size><Size name="NXL">60.50</Size><Size name="N2XL">66.50</Size><Size name="N3XL">73.50</Size></Measure><Measure name="Upper hip depth, meas. fr. upper edge" description="Upper hip depth, meas. fr. upper edge"><Size name="NS">20.00</Size><Size name="NM">20.00</Size><Size name="NL">20.00</Size><Size name="NXL">21.50</Size><Size name="N2XL">23.00</Size><Size name="N3XL">24.75</Size></Measure><Measure name="1/2 Upper hip width" description="1/2 Upper hip width"><Size name="NS">47.00</Size><Size name="NM">50.00</Size><Size name="NL">54.00</Size><Size name="NXL">59.50</Size><Size name="N2XL">65.00</Size><Size name="N3XL">71.25</Size></Measure><Measure name="1/2 Thigh width" description="1/2 Thigh width"><Size name="NS">30.20</Size><Size name="NM">32.00</Size><Size name="NL">34.50</Size><Size name="NXL">38.00</Size><Size name="N2XL">41.50</Size><Size name="N3XL">45.50</Size></Measure><Measure name="Knee height" description="Knee height"><Size name="NS">34.00</Size><Size name="NM">34.00</Size><Size name="NL">34.00</Size><Size name="NXL">34.00</Size><Size name="N2XL">34.00</Size><Size name="N3XL">34.00</Size></Measure><Measure name="1/2 Knee width" description="1/2 Knee width"><Size name="NS">25.00</Size><Size name="NM">26.00</Size><Size name="NL">26.75</Size><Size name="NXL">28.75</Size><Size name="N2XL">30.75</Size><Size name="N3XL">33.00</Size></Measure><Measure name="1/2 Width of trousers' hem" description="1/2 Width of trousers' hem"><Size name="NS">25.50</Size><Size name="NM">26.00</Size><Size name="NL">26.50</Size><Size name="NXL">28.00</Size><Size name="N2XL">29.50</Size><Size name="N3XL">31.25</Size></Measure><Measure name="Front rise incl. waistband" description="Front rise incl. waistband"><Size name="NS">24.00</Size><Size name="NM">26.00</Size><Size name="NL">28.00</Size><Size name="NXL">30.00</Size><Size name="N2XL">32.00</Size><Size name="N3XL">34.00</Size></Measure><Measure name="Back rise incl. waistband" description="Back rise incl. waistband"><Size name="NS">36.00</Size><Size name="NM">38.00</Size><Size name="NL">40.00</Size><Size name="NXL">43.25</Size><Size name="N2XL">46.50</Size><Size name="N3XL">50.00</Size></Measure><Measure name="Waistb. breadth" description="Waistb. breadth"><Size name="NS">5.00</Size><Size name="NM">5.00</Size><Size name="NL">5.00</Size><Size name="NXL">5.00</Size><Size name="N2XL">5.00</Size><Size name="N3XL">5.00</Size></Measure><Measure name="Inseam length" description="Inseam length"><Size name="NS">81.00</Size><Size name="NM">81.00</Size><Size name="NL">81.00</Size><Size name="NXL">81.00</Size><Size name="N2XL">81.00</Size><Size name="N3XL">81.00</Size></Measure><Measure name="Tie length" description="Tie length"><Size name="NS">134.00</Size><Size name="NM">140.00</Size><Size name="NL">149.00</Size><Size name="NXL">161.00</Size><Size name="N2XL">173.00</Size><Size name="N3XL">187.00</Size></Measure>]]></MeasurementChart><Length><![CDATA[81.00]]></Length><ActiveCatalogue cvl="Catalogue"><value><![CDATA[2012-OUTLET-WIN]]></value></ActiveCatalogue><LengthChart><![CDATA[<Size name="NS">81.00</Size><Size name="NM">81.00</Size><Size name="NL">81.00</Size><Size name="NXL">81.00</Size><Size name="N2XL">81.00</Size><Size name="N3XL">81.00</Size>]]></LengthChart><WashInstructions><WashInstruction locale="da">Vaskes med vrangen ud med lignende farver, uden optisk hvidt. Undlad iblødsætning. Strækkes i facon i våd tilstand. Stryges på bagsiden. Krymp 2-4%</WashInstruction><WashInstruction locale="de_CH">Von links waschen mit ähnlichen Farben. Buntwaschmittel ohne optische Aufheller. Nicht einweichen. In nassem Zustand in Form ziehen. Von links bügeln. Läuft ein 2-4%</WashInstruction><WashInstruction locale="en">Wash inside out with similar colours, w/o optical white. No soaking. To be stretched in shape while wet. Iron on backside. Shrink 2-4%</WashInstruction><WashInstruction locale="de">Von links waschen mit ähnlichen Farben. Buntwaschmittel ohne optische Aufheller. Nicht einweichen. In nassem Zustand in Form ziehen. Von links bügeln. Läuft ein 2-4%</WashInstruction><WashInstruction locale="nl">Binnenste buiten wassen met dezelfde kleuren, zonder optisch wit. Niet weken. In vochtige toestand, voorzichtig op maat rekken. Binnenste buiten strijken. Krimp: 2 - 4%.</WashInstruction><WashInstruction locale="sv">Tvättas med avigsidan ut med liknande färger och utan optiskt vitmedel. Undvik blötläggning. Sträcks försiktigt i vått tillstånd. Strykes på baksidan. Krymper: 2 - 4%.</WashInstruction></WashInstructions><IsLive /><LeadPicture><Resource id="130312742273681104_33319" /></LeadPicture><Resources><Resource id="130312742273681104_33319"><Year cvl="Year"><![CDATA[11]]></Year><PDMIdentifier /><CatalogAdcode cvl="CatalogAdcode"><value><![CDATA[2012-UDS2-PAUT]]></value><value><![CDATA[2012-OUTLET-WIN]]></value></CatalogAdcode><ImageType cvl="ImageType"><![CDATA[modelshots]]></ImageType><ResourceFileId><![CDATA[33319]]></ResourceFileId><MimeType><![CDATA[image/jpeg]]></MimeType><Season cvl="Season"><![CDATA[112]]></Season><AltTexts><AltText locale="da" /><AltText locale="de_CH" /><AltText locale="en" /><AltText locale="de" /><AltText locale="nl" /><AltText locale="sv" /></AltTexts><Filename>D:/inRiver/Publish/Production/Pics/130312742273681104_33319.jpg</Filename></Resource></Resources></Item><Item id="130254569264625087"><Descriptions><Description locale="da" /><Description locale="de_CH" /><Description locale="en" /><Description locale="de" /><Description locale="nl" /><Description locale="sv" /></Descriptions><AdCodes><![CDATA[<AdCode catalogue="2012-OUTLET-WIN">O</AdCode>]]></AdCodes><CinoNumber><![CDATA[11614]]></CinoNumber><Prices><![CDATA[<Catalogue name="2012-OUTLET-WIN"><Country code="DK" currency="DKK"><Size name="LS">0.01</Size><Size name="LL">0.01</Size><Size name="LXL">0.01</Size><Size name="L2XL">0.01</Size><Size name="L3XL">0.01</Size></Country><Country code="SE" currency="SEK"><Size name="LS">0.01</Size><Size name="LL">0.01</Size><Size name="LXL">0.01</Size><Size name="L2XL">0.01</Size><Size name="L3XL">0.01</Size></Country><Country code="NL" currency="EUR"><Size name="LS">0.01</Size><Size name="LL">0.01</Size><Size name="LXL">0.01</Size><Size name="L2XL">0.01</Size><Size name="L3XL">0.01</Size></Country><Country code="DE" currency="EUR"><Size name="LS">0.01</Size><Size name="LL">0.01</Size><Size name="LXL">0.01</Size><Size name="L2XL">0.01</Size><Size name="L3XL">0.01</Size></Country><Country code="CH" currency="SFR"><Size name="LS">0.01</Size><Size name="LL">0.01</Size><Size name="LXL">0.01</Size><Size name="L2XL">0.01</Size><Size name="L3XL">0.01</Size></Country><Country code="GB" currency="GBP"><Size name="S">0.01</Size><Size name="LL">0.01</Size><Size name="LXL">0.01</Size><Size name="L2XL">0.01</Size><Size name="L3XL">0.01</Size></Country></Catalogue>]]></Prices><Portals><Portal locale="da" /><Portal locale="de_CH" /><Portal locale="en" /><Portal locale="de" /><Portal locale="nl" /><Portal locale="sv" /></Portals><WashTemperature cvl="WashIcon" /><Inspirations><Inspiration locale="da" /><Inspiration locale="de_CH" /><Inspiration locale="en" /><Inspiration locale="de" /><Inspiration locale="nl" /><Inspiration locale="sv" /></Inspirations><Color cvl="Color"><![CDATA[6015]]></Color><ProductSubGroup /><Sizess><Sizes locale="da">LS-LM-LL-LXL-L2XL-L3XL</Sizes><Sizes locale="de_CH">LS-LM-LL-LXL-L2XL-L3XL</Sizes><Sizes locale="en">LS-LM-LL-LXL-L2XL-L3XL</Sizes><Sizes locale="de">LS-LM-LL-LXL-L2XL-L3XL</Sizes><Sizes locale="nl">LS-LM-LL-LXL-L2XL-L3XL</Sizes><Sizes locale="sv">LS-LM-LL-LXL-L2XL-L3XL</Sizes></Sizess><WashIcon cvl="WashIcon"><value><![CDATA[10700]]></value><value><![CDATA[20100]]></value><value><![CDATA[50100]]></value><value><![CDATA[30200]]></value><value><![CDATA[40500]]></value></WashIcon><ColorGroup><![CDATA[Purple]]></ColorGroup><MeasurementChart><![CDATA[<Measure name="1/2 Waist/-band width" description="1/2 Waist/-band width"><Size name="LS">35.00</Size><Size name="LM">38.00</Size><Size name="LL">42.50</Size><Size name="LXL">48.50</Size><Size name="L2XL">54.50</Size><Size name="L3XL">61.50</Size></Measure><Measure name="1/2 Waist/-band width, stret." description="1/2 Waist/-band width, stret."><Size name="LS">47.00</Size><Size name="LM">50.00</Size><Size name="LL">54.50</Size><Size name="LXL">60.50</Size><Size name="L2XL">66.50</Size><Size name="L3XL">73.50</Size></Measure><Measure name="Upper hip depth, meas. fr. upper edge" description="Upper hip depth, meas. fr. upper edge"><Size name="LS">20.00</Size><Size name="LM">20.00</Size><Size name="LL">20.00</Size><Size name="LXL">21.50</Size><Size name="L2XL">23.00</Size><Size name="L3XL">24.75</Size></Measure><Measure name="1/2 Upper hip width" description="1/2 Upper hip width"><Size name="LS">47.00</Size><Size name="LM">50.00</Size><Size name="LL">54.00</Size><Size name="LXL">59.50</Size><Size name="L2XL">65.00</Size><Size name="L3XL">71.25</Size></Measure><Measure name="1/2 Thigh width" description="1/2 Thigh width"><Size name="LS">30.20</Size><Size name="LM">32.00</Size><Size name="LL">34.50</Size><Size name="LXL">38.00</Size><Size name="L2XL">41.50</Size><Size name="L3XL">45.50</Size></Measure><Measure name="Knee height" description="Knee height"><Size name="LS">37.00</Size><Size name="LM">37.00</Size><Size name="LL">37.00</Size><Size name="LXL">37.00</Size><Size name="L2XL">37.00</Size><Size name="L3XL">37.00</Size></Measure><Measure name="1/2 Knee width" description="1/2 Knee width"><Size name="LS">25.00</Size><Size name="LM">26.00</Size><Size name="LL">26.75</Size><Size name="LXL">28.75</Size><Size name="L2XL">30.75</Size><Size name="L3XL">33.00</Size></Measure><Measure name="1/2 Width of trousers' hem" description="1/2 Width of trousers' hem"><Size name="LS">25.50</Size><Size name="LM">26.00</Size><Size name="LL">26.50</Size><Size name="LXL">28.00</Size><Size name="L2XL">29.50</Size><Size name="L3XL">31.25</Size></Measure><Measure name="Front rise incl. waistband" description="Front rise incl. waistband"><Size name="LS">24.00</Size><Size name="LM">26.00</Size><Size name="LL">28.00</Size><Size name="LXL">30.00</Size><Size name="L2XL">32.00</Size><Size name="L3XL">34.00</Size></Measure><Measure name="Back rise incl. waistband" description="Back rise incl. waistband"><Size name="LS">36.00</Size><Size name="LM">38.00</Size><Size name="LL">40.00</Size><Size name="LXL">43.25</Size><Size name="L2XL">46.50</Size><Size name="L3XL">50.00</Size></Measure><Measure name="Waistb. breadth" description="Waistb. breadth"><Size name="LS">5.00</Size><Size name="LM">5.00</Size><Size name="LL">5.00</Size><Size name="LXL">5.00</Size><Size name="L2XL">5.00</Size><Size name="L3XL">5.00</Size></Measure><Measure name="Inseam length" description="Inseam length"><Size name="LS">86.00</Size><Size name="LM">86.00</Size><Size name="LL">86.00</Size><Size name="LXL">86.00</Size><Size name="L2XL">86.00</Size><Size name="L3XL">86.00</Size></Measure><Measure name="Tie length" description="Tie length"><Size name="LS">134.00</Size><Size name="LM">140.00</Size><Size name="LL">149.00</Size><Size name="LXL">161.00</Size><Size name="L2XL">173.00</Size><Size name="L3XL">187.00</Size></Measure>]]></MeasurementChart><Length /><ActiveCatalogue cvl="Catalogue"><value><![CDATA[2012-OUTLET-WIN]]></value></ActiveCatalogue><LengthChart><![CDATA[<Size name="LS">86.00</Size><Size name="LM">86.00</Size><Size name="LL">86.00</Size><Size name="LXL">86.00</Size><Size name="L2XL">86.00</Size><Size name="L3XL">86.00</Size>]]></LengthChart><WashInstructions><WashInstruction locale="da">Vaskes med vrangen ud med lignende farver, uden optisk hvidt. Undlad iblødsætning. Strækkes i facon i våd tilstand. Stryges på bagsiden. Krymp 2-4%</WashInstruction><WashInstruction locale="de_CH">Von links waschen mit ähnlichen Farben. Buntwaschmittel ohne optische Aufheller. Nicht einweichen. In nassem Zustand in Form ziehen. Von links bügeln. Läuft ein 2-4%</WashInstruction><WashInstruction locale="en">Wash inside out with similar colours, w/o optical white. No soaking. To be stretched in shape while wet. Iron on backside. Shrink 2-4%</WashInstruction><WashInstruction locale="de">Von links waschen mit ähnlichen Farben. Buntwaschmittel ohne optische Aufheller. Nicht einweichen. In nassem Zustand in Form ziehen. Von links bügeln. Läuft ein 2-4%</WashInstruction><WashInstruction locale="nl">Binnenste buiten wassen met dezelfde kleuren, zonder optisch wit. Niet weken. In vochtige toestand, voorzichtig op maat rekken. Binnenste buiten strijken. Krimp: 2 - 4%.</WashInstruction><WashInstruction locale="sv">Tvättas med avigsidan ut med liknande färger och utan optiskt vitmedel. Undvik blötläggning. Sträcks försiktigt i vått tillstånd. Strykes på baksidan. Krymper: 2 - 4%.</WashInstruction></WashInstructions><IsLive /><LeadPicture><Resource id="130312742273681104_33319" /></LeadPicture><Resources><Resource id="130312742273681104_33319"><Year cvl="Year"><![CDATA[11]]></Year><PDMIdentifier /><CatalogAdcode cvl="CatalogAdcode"><value><![CDATA[2012-UDS2-PAUT]]></value><value><![CDATA[2012-OUTLET-WIN]]></value></CatalogAdcode><ImageType cvl="ImageType"><![CDATA[modelshots]]></ImageType><ResourceFileId><![CDATA[33319]]></ResourceFileId><MimeType><![CDATA[image/jpeg]]></MimeType><Season cvl="Season"><![CDATA[112]]></Season><AltTexts><AltText locale="da" /><AltText locale="de_CH" /><AltText locale="en" /><AltText locale="de" /><AltText locale="nl" /><AltText locale="sv" /></AltTexts><Filename>D:/inRiver/Publish/Production/Pics/130312742273681104_33319.jpg</Filename></Resource></Resources></Item></Items><Assortments><Assortment id="134555954350124061" order="31" /></Assortments><Resources><Resource id="131676783121560574_27268"><Year cvl="Year" /><PDMIdentifier /><CatalogAdcode cvl="CatalogAdcode" /><ImageType cvl="ImageType"><![CDATA[drawings]]></ImageType><ResourceFileId><![CDATA[27268]]></ResourceFileId><MimeType><![CDATA[image/jpeg]]></MimeType><Season cvl="Season" /><AltTexts><AltText locale="da" /><AltText locale="de_CH" /><AltText locale="en" /><AltText locale="de" /><AltText locale="nl" /><AltText locale="sv" /></AltTexts><Filename>D:/inRiver/Publish/Production/Pics/131676783121560574_27268.jpg</Filename></Resource><Resource id="130312742273681104_33319"><Year cvl="Year"><![CDATA[11]]></Year><PDMIdentifier /><CatalogAdcode cvl="CatalogAdcode"><value><![CDATA[2012-UDS2-PAUT]]></value><value><![CDATA[2012-OUTLET-WIN]]></value></CatalogAdcode><ImageType cvl="ImageType"><![CDATA[modelshots]]></ImageType><ResourceFileId><![CDATA[33319]]></ResourceFileId><MimeType><![CDATA[image/jpeg]]></MimeType><Season cvl="Season"><![CDATA[112]]></Season><AltTexts><AltText locale="da" /><AltText locale="de_CH" /><AltText locale="en" /><AltText locale="de" /><AltText locale="nl" /><AltText locale="sv" /></AltTexts><Filename>D:/inRiver/Publish/Production/Pics/130312742273681104_33319.jpg</Filename></Resource></Resources></Product>
