<?xml version="1.0" encoding="UTF-8"?>
<Product id="133188841161499163" action="updated"><Catalogue cvl="Catalogue"><value><![CDATA[2012-UDS4-PAUT]]></value><value><![CDATA[2012-UDS2-PAUT]]></value><value><![CDATA[2012-UDS3-PAUT]]></value></Catalogue><Fitting cvl="Fitting"><![CDATA[No-icon]]></Fitting><SizeGroup><![CDATA[<SizeRange name="36-48">36,38,40,42,44,46,48</SizeRange>]]></SizeGroup><DescriptionCatalogues><DescriptionCatalogue locale="da">Model i blød elastisk microfiber med print og kontrastfarvet blonde.</DescriptionCatalogue><DescriptionCatalogue locale="de_CH">Modell aus weicher, elastischer Microfaser mit Print und kontrastfarbener Spitze.</DescriptionCatalogue><DescriptionCatalogue locale="en">Design in soft elasticated microfibre with print and contrasting lace.</DescriptionCatalogue><DescriptionCatalogue locale="de">Modell aus weicher, elastischer Microfaser mit Print und kontrastfarbener Spitze.</DescriptionCatalogue><DescriptionCatalogue locale="nl">Model van zachte elastische microfiber kwaliteit met print en contrastkleurig kantwerk.</DescriptionCatalogue><DescriptionCatalogue locale="sv">Modell i mjuk, elastisk mikrofiber med tryckt mönster och kontrastfärgad spets.</DescriptionCatalogue></DescriptionCatalogues><Animal_Origin>false</Animal_Origin><MeasureHeading cvl="MeasureHeading"><value><![CDATA[Size]]></value></MeasureHeading><MeasurementDescriptions><MeasurementDescription locale="da" /><MeasurementDescription locale="de_CH" /><MeasurementDescription locale="en" /><MeasurementDescription locale="de" /><MeasurementDescription locale="nl" /><MeasurementDescription locale="sv" /></MeasurementDescriptions><Program cvl="Program"><![CDATA[L]]></Program><IsLive /><Composition cvl="Composition"><![CDATA[536]]></Composition><ProductMainGroup cvl="ProductMainGroup"><![CDATA[40]]></ProductMainGroup><SizeGuide /><SizeGroupName><![CDATA[36-48]]></SizeGroupName><MeasurementImage /><ProductStatus cvl="ProductStatus" /><translationReady /><Season cvl="Season"><value><![CDATA[122]]></value></Season><Concept cvl="Concept"><![CDATA[S]]></Concept><DisplaySize>true</DisplaySize><MeasureChartAbrv /><ProductSubGroup cvl="ProductSubGroup" /><LengthDescription cvl="LengthDescription" /><ProductGroup cvl="ProductGroup"><![CDATA[4022]]></ProductGroup><DescriptionWebs><DescriptionWeb locale="da" /><DescriptionWeb locale="de_CH" /><DescriptionWeb locale="en" /><DescriptionWeb locale="de" /><DescriptionWeb locale="nl" /><DescriptionWeb locale="sv" /></DescriptionWebs><HeaderWebs><HeaderWeb locale="da">Trusse</HeaderWeb><HeaderWeb locale="de_CH">Slip</HeaderWeb><HeaderWeb locale="en">Briefs</HeaderWeb><HeaderWeb locale="de">Slip</HeaderWeb><HeaderWeb locale="nl">Slip</HeaderWeb><HeaderWeb locale="sv">Trosa</HeaderWeb></HeaderWebs><CompositionFoders><CompositionFoder locale="da" /><CompositionFoder locale="de_CH" /><CompositionFoder locale="en" /><CompositionFoder locale="de" /><CompositionFoder locale="nl" /><CompositionFoder locale="sv" /></CompositionFoders><DescriptionPDMs><DescriptionPDM locale="da">brief w. double lace edge Shell fabric/Yderstof/Oberstoff 86% Polyester 14% Elastane/Elasthan Vask 40°</DescriptionPDM><DescriptionPDM locale="de_CH" /><DescriptionPDM locale="en" /><DescriptionPDM locale="de" /><DescriptionPDM locale="nl" /><DescriptionPDM locale="sv" /></DescriptionPDMs><usedInSpread /><LengthImage /><DisplayComposition>true</DisplayComposition><StyleNbr><![CDATA[6665]]></StyleNbr><HeaderPDMs><HeaderPDM locale="da">Trusse</HeaderPDM><HeaderPDM locale="de_CH" /><HeaderPDM locale="en" /><HeaderPDM locale="de" /><HeaderPDM locale="nl" /><HeaderPDM locale="sv" /></HeaderPDMs><Items><Item id="133188841109892161"><Descriptions><Description locale="da" /><Description locale="de_CH" /><Description locale="en" /><Description locale="de" /><Description locale="nl" /><Description locale="sv" /></Descriptions><AdCodes><![CDATA[<AdCode catalogue="2012-UDS4-PAUT">8</AdCode><AdCode catalogue="2012-UDS2-PAUT">9</AdCode><AdCode catalogue="2012-UDS3-PAUT">8</AdCode>]]></AdCodes><CinoNumber><![CDATA[03665]]></CinoNumber><Prices><![CDATA[<Catalogue name="2012-UDS4-PAUT"><Country code="DK" currency="DKK"><Size name="36">0.01</Size><Size name="38">0.01</Size><Size name="40">0.01</Size><Size name="42">0.01</Size><Size name="44">0.01</Size><Size name="46">0.01</Size><Size name="48">0.01</Size></Country><Country code="SE" currency="SEK"><Size name="36">0.01</Size><Size name="38">0.01</Size><Size name="40">0.01</Size><Size name="42">0.01</Size><Size name="44">0.01</Size><Size name="46">0.01</Size><Size name="48">0.01</Size></Country><Country code="NL" currency="EUR"><Size name="36">0.01</Size><Size name="38">0.01</Size><Size name="40">0.01</Size><Size name="42">0.01</Size><Size name="44">0.01</Size><Size name="46">0.01</Size><Size name="48">0.01</Size></Country><Country code="DE" currency="EUR"><Size name="36">0.01</Size><Size name="38">0.01</Size><Size name="40">0.01</Size><Size name="42">0.01</Size><Size name="44">0.01</Size><Size name="46">0.01</Size><Size name="48">0.01</Size></Country><Country code="CH" currency="SFR"><Size name="36">0.01</Size><Size name="38">0.01</Size><Size name="40">0.01</Size><Size name="42">0.01</Size><Size name="44">0.01</Size><Size name="46">0.01</Size><Size name="48">0.01</Size></Country><Country code="GB" currency="GBP"><Size name="10">0.01</Size><Size name="12">0.01</Size><Size name="14">0.01</Size><Size name="16">0.01</Size><Size name="18">0.01</Size><Size name="20">0.01</Size><Size name="22">0.01</Size></Country></Catalogue><Catalogue name="2012-UDS2-PAUT"><Country code="DK" currency="DKK"><Size name="36">44.95</Size><Size name="38">44.95</Size><Size name="40">44.95</Size><Size name="42">44.95</Size><Size name="44">44.95</Size><Size name="46">44.95</Size><Size name="48">44.95</Size></Country><Country code="SE" currency="SEK"><Size name="36">59.95</Size><Size name="38">59.95</Size><Size name="40">59.95</Size><Size name="42">59.95</Size><Size name="44">59.95</Size><Size name="46">59.95</Size><Size name="48">59.95</Size></Country><Country code="NL" currency="EUR"><Size name="36">6.95</Size><Size name="38">6.95</Size><Size name="40">6.95</Size><Size name="42">6.95</Size><Size name="44">6.95</Size><Size name="46">6.95</Size><Size name="48">6.95</Size></Country><Country code="DE" currency="EUR"><Size name="36">9.95</Size><Size name="38">9.95</Size><Size name="40">9.95</Size><Size name="42">9.95</Size><Size name="44">9.95</Size><Size name="46">9.95</Size><Size name="48">9.95</Size></Country><Country code="CH" currency="SFR"><Size name="36">14.95</Size><Size name="38">14.95</Size><Size name="40">14.95</Size><Size name="42">14.95</Size><Size name="44">14.95</Size><Size name="46">14.95</Size><Size name="48">14.95</Size></Country><Country code="GB" currency="GBP"><Size name="10">7.00</Size><Size name="12">7.00</Size><Size name="14">7.00</Size><Size name="16">7.00</Size><Size name="18">7.00</Size><Size name="20">7.00</Size><Size name="22">7.00</Size></Country></Catalogue><Catalogue name="2012-UDS3-PAUT"><Country code="DK" currency="DKK"><Size name="36">0.01</Size><Size name="38">0.01</Size><Size name="40">0.01</Size><Size name="42">0.01</Size><Size name="44">0.01</Size><Size name="46">0.01</Size><Size name="48">0.01</Size></Country><Country code="SE" currency="SEK"><Size name="36">0.01</Size><Size name="38">0.01</Size><Size name="40">0.01</Size><Size name="42">0.01</Size><Size name="44">0.01</Size><Size name="46">0.01</Size><Size name="48">0.01</Size></Country><Country code="NL" currency="EUR"><Size name="36">0.01</Size><Size name="38">0.01</Size><Size name="40">0.01</Size><Size name="42">0.01</Size><Size name="44">0.01</Size><Size name="46">0.01</Size><Size name="48">0.01</Size></Country><Country code="DE" currency="EUR"><Size name="36">0.01</Size><Size name="38">0.01</Size><Size name="40">0.01</Size><Size name="42">0.01</Size><Size name="44">0.01</Size><Size name="46">0.01</Size><Size name="48">0.01</Size></Country><Country code="CH" currency="SFR"><Size name="36">0.01</Size><Size name="38">0.01</Size><Size name="40">0.01</Size><Size name="42">0.01</Size><Size name="44">0.01</Size><Size name="46">0.01</Size><Size name="48">0.01</Size></Country><Country code="GB" currency="GBP"><Size name="10">0.01</Size><Size name="12">0.01</Size><Size name="14">0.01</Size><Size name="16">0.01</Size><Size name="18">0.01</Size><Size name="20">0.01</Size><Size name="22">0.01</Size></Country></Catalogue>]]></Prices><Portals><Portal locale="da" /><Portal locale="de_CH" /><Portal locale="en" /><Portal locale="de" /><Portal locale="nl" /><Portal locale="sv" /></Portals><WashTemperature cvl="WashIcon" /><Inspirations><Inspiration locale="da" /><Inspiration locale="de_CH" /><Inspiration locale="en" /><Inspiration locale="de" /><Inspiration locale="nl" /><Inspiration locale="sv" /></Inspirations><Color cvl="Color"><![CDATA[0081]]></Color><ProductSubGroup /><Sizess><Sizes locale="da">36-38-40-42-44-46-48</Sizes><Sizes locale="de_CH">36-38-40-42-44-46-48</Sizes><Sizes locale="en">10-12-14-16-18-20-22</Sizes><Sizes locale="de">36-38-40-42-44-46-48</Sizes><Sizes locale="nl">36-38-40-42-44-46-48</Sizes><Sizes locale="sv">36-38-40-42-44-46-48</Sizes></Sizess><WashIcon cvl="WashIcon"><value><![CDATA[10700]]></value><value><![CDATA[20100]]></value><value><![CDATA[50100]]></value><value><![CDATA[30100]]></value><value><![CDATA[40100]]></value></WashIcon><ColorGroup><![CDATA[White]]></ColorGroup><MeasurementChart><![CDATA[<Measure name="1/2 Waist/-band width" description="1/2 Waist/-band width"><Size name="36">32.00</Size><Size name="38">34.00</Size><Size name="40">36.00</Size><Size name="42">38.00</Size><Size name="44">40.00</Size><Size name="46">42.00</Size><Size name="48">44.00</Size></Measure><Measure name="1/2 Waist/-band width, stret." description="1/2 Waist/-band width, stret."><Size name="36">48.00</Size><Size name="38">50.00</Size><Size name="40">52.00</Size><Size name="42">54.00</Size><Size name="44">56.00</Size><Size name="46">58.00</Size><Size name="48">60.00</Size></Measure><Measure name="Girth of leg cutting" description="Girth of leg cutting"><Size name="36">52.00</Size><Size name="38">54.00</Size><Size name="40">56.20</Size><Size name="42">58.40</Size><Size name="44">60.60</Size><Size name="46">62.80</Size><Size name="48">65.00</Size></Measure><Measure name="Side length, meas. fr. upper edge" description="Side length, meas. fr. upper edge"><Size name="36">6.50</Size><Size name="38">6.50</Size><Size name="40">6.50</Size><Size name="42">6.50</Size><Size name="44">6.50</Size><Size name="46">7.50</Size><Size name="48">7.50</Size></Measure><Measure name="Body rise of slip, front" description="Body rise of slip, front"><Size name="36">15.50</Size><Size name="38">16.50</Size><Size name="40">18.00</Size><Size name="42">19.50</Size><Size name="44">21.20</Size><Size name="46">22.90</Size><Size name="48">24.60</Size></Measure><Measure name="Body rise of slip, back" description="Body rise of slip, back"><Size name="36">19.00</Size><Size name="38">20.00</Size><Size name="40">21.00</Size><Size name="42">22.00</Size><Size name="44">23.00</Size><Size name="46">24.00</Size><Size name="48">25.00</Size></Measure><Measure name="Gore breadth front" description="Gore breadth front"><Size name="36">6.30</Size><Size name="38">6.30</Size><Size name="40">6.30</Size><Size name="42">6.30</Size><Size name="44">6.30</Size><Size name="46">6.60</Size><Size name="48">6.60</Size></Measure><Measure name="Gore breadt back" description="Gore breadt back"><Size name="36">12.70</Size><Size name="38">12.70</Size><Size name="40">12.70</Size><Size name="42">12.70</Size><Size name="44">12.70</Size><Size name="46">13.20</Size><Size name="48">13.20</Size></Measure><Measure name="Gore length" description="Gore length"><Size name="36">12.50</Size><Size name="38">12.50</Size><Size name="40">12.50</Size><Size name="42">12.50</Size><Size name="44">12.50</Size><Size name="46">12.50</Size><Size name="48">12.50</Size></Measure>]]></MeasurementChart><Length /><ActiveCatalogue cvl="Catalogue"><value><![CDATA[2012-UDS4-PAUT]]></value><value><![CDATA[2012-UDS2-PAUT]]></value><value><![CDATA[2012-UDS3-PAUT]]></value></ActiveCatalogue><LengthChart /><WashInstructions><WashInstruction locale="da" /><WashInstruction locale="de_CH" /><WashInstruction locale="en" /><WashInstruction locale="de" /><WashInstruction locale="nl" /><WashInstruction locale="sv" /></WashInstructions><IsLive /><LeadPicture><Resource id="133473804944257091_54371" /></LeadPicture><Resources><Resource id="133473804944257091_54371"><OriginalFilename><![CDATA[122S_08_02_V042.jpg]]></OriginalFilename><Year cvl="Year"><![CDATA[12]]></Year><PDMIdentifier /><CatalogAdcode cvl="CatalogAdcode"><value><![CDATA[2012-SEC-WIN]]></value><value><![CDATA[2012-BAP-PAUT]]></value><value><![CDATA[2012-UDS1-PAUT]]></value><value><![CDATA[2012-UDS2-PAUT]]></value><value><![CDATA[2012-UDS3-PAUT]]></value></CatalogAdcode><ImageType cvl="ImageType"><![CDATA[modelshots]]></ImageType><ResourceFileId><![CDATA[54371]]></ResourceFileId><MimeType><![CDATA[image/jpeg]]></MimeType><Season cvl="Season"><![CDATA[122]]></Season><AltTexts><AltText locale="da" /><AltText locale="de_CH" /><AltText locale="en" /><AltText locale="de" /><AltText locale="nl" /><AltText locale="sv" /></AltTexts><Filename>D:/inRiver/Publish/Production/Pics/133473804944257091_54371.jpg</Filename></Resource></Resources></Item></Items><Assortments><Assortment id="134555950559671347" order="142" /><Assortment id="134555952204848308" order="97" /></Assortments><Resources /></Product>
