<?xml version="1.0" encoding="UTF-8"?>
<Product id="13135032489761832"><Catalogue cvl="Catalogue"><value><![CDATA[2013-OUTLET-SUM]]></value></Catalogue><Fitting cvl="Fitting"><![CDATA[No-icon]]></Fitting><SizeGroup><![CDATA[<SizeRange name="F_36-42">36,37,38,39,40,41,42</SizeRange>]]></SizeGroup><DescriptionCatalogues><DescriptionCatalogue locale="da">Tåsandal med god comfort og dekorative perler. Indvendig ruskindssål.</DescriptionCatalogue><DescriptionCatalogue locale="de_CH">Zehensandale mit gutem Tragekomfort und dekorativen Perlen. Innensohle aus Wildleder.</DescriptionCatalogue><DescriptionCatalogue locale="en">Comfortable toe sandal with decorative beading. Suede insole.</DescriptionCatalogue><DescriptionCatalogue locale="de">Zehensandale mit gutem Tragekomfort und dekorativen Perlen. Innensohle aus Wildleder.</DescriptionCatalogue><DescriptionCatalogue locale="nl">Comfortabele teensandaal met decoratieve kralen. Suède binnenzool.</DescriptionCatalogue><DescriptionCatalogue locale="sv">Bekväm tåsandal med dekorpärlor. Innersula i mocka.</DescriptionCatalogue></DescriptionCatalogues><Animal_Origin>false</Animal_Origin><MeasureHeading cvl="MeasureHeading"><value><![CDATA[Size]]></value></MeasureHeading><MeasurementDescriptions><MeasurementDescription locale="da" /><MeasurementDescription locale="de_CH" /><MeasurementDescription locale="en" /><MeasurementDescription locale="de" /><MeasurementDescription locale="nl" /><MeasurementDescription locale="sv" /></MeasurementDescriptions><Program cvl="Program"><![CDATA[D]]></Program><IsLive /><Composition cvl="Composition"><![CDATA[899]]></Composition><ProductMainGroup cvl="ProductMainGroup"><![CDATA[14]]></ProductMainGroup><SizeGuide /><SizeGroupName><![CDATA[F_36-42]]></SizeGroupName><MeasurementImage /><ProductStatus cvl="ProductStatus" /><translationReady /><Season cvl="Season"><value><![CDATA[131]]></value></Season><Concept cvl="Concept"><![CDATA[B]]></Concept><DisplaySize>true</DisplaySize><MeasureChartAbrv /><ProductSubGroup cvl="ProductSubGroup" /><LengthDescription cvl="LengthDescription" /><ProductGroup cvl="ProductGroup"><![CDATA[1400]]></ProductGroup><DescriptionWebs><DescriptionWeb locale="da" /><DescriptionWeb locale="de_CH" /><DescriptionWeb locale="en" /><DescriptionWeb locale="de" /><DescriptionWeb locale="nl" /><DescriptionWeb locale="sv" /></DescriptionWebs><HeaderWebs><HeaderWeb locale="da">Skindsandal</HeaderWeb><HeaderWeb locale="de_CH">Ledersandale</HeaderWeb><HeaderWeb locale="en">Leather sandals</HeaderWeb><HeaderWeb locale="de">Ledersandale</HeaderWeb><HeaderWeb locale="nl">Leren sandaal</HeaderWeb><HeaderWeb locale="sv">Läder sandaler</HeaderWeb></HeaderWebs><CompositionFoders><CompositionFoder locale="da" /><CompositionFoder locale="de_CH" /><CompositionFoder locale="en" /><CompositionFoder locale="de" /><CompositionFoder locale="nl" /><CompositionFoder locale="sv" /></CompositionFoders><DescriptionPDMs><DescriptionPDM locale="da">Comfort leather sandal with toe strap, decoration at upper. Shell fabric/Yderstof/Oberstoff 80% Leather/Læder/Leder 20% Cotton/Bomuld/Baumwolle</DescriptionPDM><DescriptionPDM locale="de_CH" /><DescriptionPDM locale="en" /><DescriptionPDM locale="de" /><DescriptionPDM locale="nl" /><DescriptionPDM locale="sv" /></DescriptionPDMs><usedInSpread /><LengthImage /><DisplayComposition>true</DisplayComposition><StyleNbr><![CDATA[5160]]></StyleNbr><HeaderPDMs><HeaderPDM locale="da">Skindsandal</HeaderPDM><HeaderPDM locale="de_CH" /><HeaderPDM locale="en" /><HeaderPDM locale="de" /><HeaderPDM locale="nl" /><HeaderPDM locale="sv" /></HeaderPDMs><Items><Item id="131479411569763361"><Descriptions><Description locale="da" /><Description locale="de_CH" /><Description locale="en" /><Description locale="de" /><Description locale="nl" /><Description locale="sv" /></Descriptions><AdCodes><![CDATA[<AdCode catalogue="2013-OUTLET-SUM">G</AdCode>]]></AdCodes><CinoNumber><![CDATA[75151]]></CinoNumber><Prices><![CDATA[<Catalogue name="2013-OUTLET-SUM"><Country code="DK" currency="DKK"><Size name="37">0.01</Size><Size name="38">0.01</Size><Size name="39">0.01</Size><Size name="41">0.01</Size><Size name="42">0.01</Size></Country><Country code="SE" currency="SEK"><Size name="37">0.01</Size><Size name="38">0.01</Size><Size name="39">0.01</Size><Size name="41">0.01</Size><Size name="42">0.01</Size></Country><Country code="NL" currency="EUR"><Size name="37">0.01</Size><Size name="38">0.01</Size><Size name="39">0.01</Size><Size name="41">0.01</Size><Size name="42">0.01</Size></Country><Country code="DE" currency="EUR"><Size name="37">0.01</Size><Size name="38">0.01</Size><Size name="39">0.01</Size><Size name="41">0.01</Size><Size name="42">0.01</Size></Country><Country code="CH" currency="SFR"><Size name="37">0.01</Size><Size name="38">0.01</Size><Size name="39">0.01</Size><Size name="41">0.01</Size><Size name="42">0.01</Size></Country><Country code="GB" currency="GBP"><Size name="37">0.01</Size><Size name="38">0.01</Size><Size name="39">0.01</Size><Size name="41">0.01</Size><Size name="42">0.01</Size></Country></Catalogue>]]></Prices><Portals><Portal locale="da" /><Portal locale="de_CH" /><Portal locale="en" /><Portal locale="de" /><Portal locale="nl" /><Portal locale="sv" /></Portals><WashTemperature cvl="WashIcon" /><Inspirations><Inspiration locale="da" /><Inspiration locale="de_CH" /><Inspiration locale="en" /><Inspiration locale="de" /><Inspiration locale="nl" /><Inspiration locale="sv" /></Inspirations><Color cvl="Color"><![CDATA[7002]]></Color><ProductSubGroup /><Sizess><Sizes locale="da">36-37-38-39-40-41-42</Sizes><Sizes locale="de_CH">36-37-38-39-40-41-42</Sizes><Sizes locale="en">36-37-38-39-40-41-42</Sizes><Sizes locale="de">36-37-38-39-40-41-42</Sizes><Sizes locale="nl">36-37-38-39-40-41-42</Sizes><Sizes locale="sv">36-37-38-39-40-41-42</Sizes></Sizess><WashIcon cvl="WashIcon" /><ColorGroup><![CDATA[Brown]]></ColorGroup><MeasurementChart><![CDATA[<Measure name="Heel height" description="Heel height"><Size name="36">0.00</Size><Size name="37">0.00</Size><Size name="38">0.00</Size><Size name="39">0.00</Size><Size name="40">0.00</Size><Size name="41">0.00</Size><Size name="42">0.00</Size></Measure><Measure name="Inside length" description="Inside length"><Size name="36">23.20</Size><Size name="37">23.80</Size><Size name="38">24.40</Size><Size name="39">25.00</Size><Size name="40">25.60</Size><Size name="41">26.20</Size><Size name="42">26.80</Size></Measure><Measure name="Leg circumference" description="Leg circumference"><Size name="36">0.00</Size><Size name="37">0.00</Size><Size name="38">0.00</Size><Size name="39">0.00</Size><Size name="40">0.00</Size><Size name="41">0.00</Size><Size name="42">0.00</Size></Measure><Measure name="Leg height" description="Leg height"><Size name="36">0.00</Size><Size name="37">0.00</Size><Size name="38">0.00</Size><Size name="39">0.00</Size><Size name="40">0.00</Size><Size name="41">0.00</Size><Size name="42">0.00</Size></Measure>]]></MeasurementChart><Length /><ActiveCatalogue cvl="Catalogue"><value><![CDATA[2013-OUTLET-SUM]]></value></ActiveCatalogue><LengthChart /><WashInstructions><WashInstruction locale="da" /><WashInstruction locale="de_CH" /><WashInstruction locale="en" /><WashInstruction locale="de" /><WashInstruction locale="nl" /><WashInstruction locale="sv" /></WashInstructions><IsLive /><LeadPicture><Resource id="131555227495374483_44883" /></LeadPicture><Resources><Resource id="13219585086148707_39785"><Year cvl="Year"><![CDATA[12]]></Year><PDMIdentifier /><CatalogAdcode cvl="CatalogAdcode"><value><![CDATA[2012-BAP-Prespring]]></value><value><![CDATA[2012-Favorit-Sum]]></value></CatalogAdcode><ImageType cvl="ImageType"><![CDATA[modelshots]]></ImageType><ResourceFileId><![CDATA[39785]]></ResourceFileId><MimeType><![CDATA[image/jpeg]]></MimeType><Season cvl="Season"><![CDATA[121]]></Season><AltTexts><AltText locale="da" /><AltText locale="de_CH" /><AltText locale="en" /><AltText locale="de" /><AltText locale="nl" /><AltText locale="sv" /></AltTexts><Filename>D:/inRiver/Publish/Production/Pics/13219585086148707_39785.jpg</Filename></Resource><Resource id="1330508991006896_41867"><Year cvl="Year"><![CDATA[12]]></Year><PDMIdentifier /><CatalogAdcode cvl="CatalogAdcode"><value><![CDATA[2012-Favorit-Sum]]></value></CatalogAdcode><ImageType cvl="ImageType"><![CDATA[modelshots]]></ImageType><ResourceFileId><![CDATA[41867]]></ResourceFileId><MimeType><![CDATA[image/jpeg]]></MimeType><Season cvl="Season"><![CDATA[121]]></Season><AltTexts><AltText locale="da" /><AltText locale="de_CH" /><AltText locale="en" /><AltText locale="de" /><AltText locale="nl" /><AltText locale="sv" /></AltTexts><Filename>D:/inRiver/Publish/Production/Pics/1330508991006896_41867.jpg</Filename></Resource><Resource id="132247577800165680_47001"><Year cvl="Year"><![CDATA[2012]]></Year><PDMIdentifier /><CatalogAdcode cvl="CatalogAdcode"><value><![CDATA[2012-BAP-Sum]]></value><value><![CDATA[2012-Favorit-Sum]]></value><value><![CDATA[2012-Udsalg2-Sum]]></value><value><![CDATA[2012-Udsalg4-Sum]]></value></CatalogAdcode><ImageType cvl="ImageType"><![CDATA[modelshots]]></ImageType><ResourceFileId><![CDATA[47001]]></ResourceFileId><MimeType><![CDATA[image/jpeg]]></MimeType><Season cvl="Season"><![CDATA[Summer 2012]]></Season><AltTexts><AltText locale="da" /><AltText locale="de_CH" /><AltText locale="en" /><AltText locale="de" /><AltText locale="nl" /><AltText locale="sv" /></AltTexts><Filename>D:/inRiver/Publish/Production/Pics/132247577800165680_47001.jpg</Filename></Resource><Resource id="13172099602845165_28236"><Year cvl="Year"><![CDATA[12]]></Year><PDMIdentifier /><CatalogAdcode cvl="CatalogAdcode"><value><![CDATA[2012-BAP-Sum]]></value></CatalogAdcode><ImageType cvl="ImageType"><![CDATA[modelshots]]></ImageType><ResourceFileId><![CDATA[28236]]></ResourceFileId><MimeType><![CDATA[image/jpeg]]></MimeType><Season cvl="Season"><![CDATA[121]]></Season><AltTexts><AltText locale="da" /><AltText locale="de_CH" /><AltText locale="en" /><AltText locale="de" /><AltText locale="nl" /><AltText locale="sv" /></AltTexts><Filename>D:/inRiver/Publish/Production/Pics/13172099602845165_28236.jpg</Filename></Resource><Resource id="131555227495374483_44883"><Year cvl="Year"><![CDATA[2012]]></Year><PDMIdentifier /><CatalogAdcode cvl="CatalogAdcode"><value><![CDATA[2012-BAP-Prespring]]></value><value><![CDATA[2012-BAP-Sum]]></value><value><![CDATA[2012-BAP-Jubilee-Spring]]></value><value><![CDATA[2012-Favorit-Sum]]></value><value><![CDATA[2012-Udsalg-Sum]]></value><value><![CDATA[2012-Udsalg2-Sum]]></value></CatalogAdcode><ImageType cvl="ImageType"><![CDATA[packshots]]></ImageType><ResourceFileId><![CDATA[44883]]></ResourceFileId><MimeType><![CDATA[image/jpeg]]></MimeType><Season cvl="Season"><![CDATA[121]]></Season><AltTexts><AltText locale="da" /><AltText locale="de_CH" /><AltText locale="en" /><AltText locale="de" /><AltText locale="nl" /><AltText locale="sv" /></AltTexts><Filename>D:/inRiver/Publish/Production/Pics/131555227495374483_44883.jpg</Filename></Resource><Resource id="131643769750860300_40547"><Year cvl="Year"><![CDATA[12]]></Year><PDMIdentifier /><CatalogAdcode cvl="CatalogAdcode"><value><![CDATA[2012-BAP-Prespring]]></value><value><![CDATA[2012-BAP-Jubilee-Spring]]></value><value><![CDATA[2012-Pakk2-Sum]]></value></CatalogAdcode><ImageType cvl="ImageType"><![CDATA[modelshots]]></ImageType><ResourceFileId><![CDATA[40547]]></ResourceFileId><MimeType><![CDATA[image/jpeg]]></MimeType><Season cvl="Season"><![CDATA[121]]></Season><AltTexts><AltText locale="da" /><AltText locale="de_CH" /><AltText locale="en" /><AltText locale="de" /><AltText locale="nl" /><AltText locale="sv" /></AltTexts><Filename>D:/inRiver/Publish/Production/Pics/131643769750860300_40547.jpg</Filename></Resource><Resource id="131643769685248328_40546"><Year cvl="Year"><![CDATA[12]]></Year><PDMIdentifier /><CatalogAdcode cvl="CatalogAdcode"><value><![CDATA[2012-BAP-Jubilee-Spring]]></value><value><![CDATA[2012-Pakk2-Sum]]></value><value><![CDATA[2012-Secrets-Sum]]></value><value><![CDATA[2012-BAP-Prespring]]></value></CatalogAdcode><ImageType cvl="ImageType"><![CDATA[modelshots]]></ImageType><ResourceFileId><![CDATA[40546]]></ResourceFileId><MimeType><![CDATA[image/jpeg]]></MimeType><Season cvl="Season"><![CDATA[121]]></Season><AltTexts><AltText locale="da" /><AltText locale="de_CH" /><AltText locale="en" /><AltText locale="de" /><AltText locale="nl" /><AltText locale="sv" /></AltTexts><Filename>D:/inRiver/Publish/Production/Pics/131643769685248328_40546.jpg</Filename></Resource></Resources></Item></Items><Assortments><Assortment id="134555927777377834" order="42" /></Assortments><Resources><Resource id="131555227495374483_44883"><Year cvl="Year"><![CDATA[2012]]></Year><PDMIdentifier /><CatalogAdcode cvl="CatalogAdcode"><value><![CDATA[2012-BAP-Prespring]]></value><value><![CDATA[2012-BAP-Sum]]></value><value><![CDATA[2012-BAP-Jubilee-Spring]]></value><value><![CDATA[2012-Favorit-Sum]]></value><value><![CDATA[2012-Udsalg-Sum]]></value><value><![CDATA[2012-Udsalg2-Sum]]></value></CatalogAdcode><ImageType cvl="ImageType"><![CDATA[packshots]]></ImageType><ResourceFileId><![CDATA[44883]]></ResourceFileId><MimeType><![CDATA[image/jpeg]]></MimeType><Season cvl="Season"><![CDATA[121]]></Season><AltTexts><AltText locale="da" /><AltText locale="de_CH" /><AltText locale="en" /><AltText locale="de" /><AltText locale="nl" /><AltText locale="sv" /></AltTexts><Filename>D:/inRiver/Publish/Production/Pics/131555227495374483_44883.jpg</Filename></Resource><Resource id="131555227406218463_43665"><Year cvl="Year"><![CDATA[2012]]></Year><PDMIdentifier /><CatalogAdcode cvl="CatalogAdcode"><value><![CDATA[2012-BAP-Prespring]]></value><value><![CDATA[2012-Favorit-Sum]]></value><value><![CDATA[2012-BAP-Sum]]></value></CatalogAdcode><ImageType cvl="ImageType"><![CDATA[packshots]]></ImageType><ResourceFileId><![CDATA[43665]]></ResourceFileId><MimeType><![CDATA[image/jpeg]]></MimeType><Season cvl="Season"><![CDATA[121]]></Season><AltTexts><AltText locale="da" /><AltText locale="de_CH" /><AltText locale="en" /><AltText locale="de" /><AltText locale="nl" /><AltText locale="sv" /></AltTexts><Filename>D:/inRiver/Publish/Production/Pics/131555227406218463_43665.jpg</Filename></Resource><Resource id="133413631725049321_43301"><Year cvl="Year"><![CDATA[2012]]></Year><PDMIdentifier /><CatalogAdcode cvl="CatalogAdcode"><value><![CDATA[2012-Udsalg-Sum]]></value></CatalogAdcode><ImageType cvl="ImageType"><![CDATA[packshots]]></ImageType><ResourceFileId><![CDATA[43301]]></ResourceFileId><MimeType><![CDATA[image/jpeg]]></MimeType><Season cvl="Season"><![CDATA[121]]></Season><AltTexts><AltText locale="da" /><AltText locale="de_CH" /><AltText locale="en" /><AltText locale="de" /><AltText locale="nl" /><AltText locale="sv" /></AltTexts><Filename>D:/inRiver/Publish/Production/Pics/133413631725049321_43301.jpg</Filename></Resource></Resources></Product>
