<?xml version="1.0" encoding="UTF-8"?>
<Product id="134426263794371008" action="updated"><Catalogue cvl="Catalogue"><value><![CDATA[2013-FAV-PSPR]]></value><value><![CDATA[2013-BAP-SUM]]></value><value><![CDATA[2013-BAP-PSPR]]></value></Catalogue><Fitting cvl="Fitting"><![CDATA[Regular]]></Fitting><SizeGroup><![CDATA[<SizeRange name="N34-54">N34,N36,N38,N40,N42,N44,N46,N48,N50,N52,N54</SizeRange><SizeRange name="L34-54">L34,L36,L38,L40,L42,L44,L46,L48,L50,L52,L54</SizeRange>]]></SizeGroup><DescriptionCatalogues><DescriptionCatalogue locale="da">Fast linning med bæltestropper og bindebånd. Forlommer. Lommer for- og bagpå med knap. Strop for justérbar længde. Blød vasket kvalitet. Vask 40°.</DescriptionCatalogue><DescriptionCatalogue locale="de_CH">Fester Bund mit Gürtelschlaufen und Bindeband. Taschen vorne. Geknöpfte Taschen vorne und hinten. Schlaufen zum Anpassen der Beinlänge. Weiche, gewaschene Qualität. 40° waschbar.</DescriptionCatalogue><DescriptionCatalogue locale="en">Fixed waistband with belt loops and tie cord. Front pockets. Pockets front and back with button. Strap for adjustable length. Soft washed fabric. Wash at 40°.</DescriptionCatalogue><DescriptionCatalogue locale="de">Fester Bund mit Gürtelschlaufen und Bindeband. Taschen vorne. Geknöpfte Taschen vorne und hinten. Schlaufen zum Anpassen der Beinlänge. Weiche, gewaschene Qualität. 40° waschbar.</DescriptionCatalogue><DescriptionCatalogue locale="nl">Vaste tailleband met riemlussen en koord. Zakken voor. Zakken voor en achter met knoop. Bandje voor een verstelbare lengte. Voorgewassen kwaliteit. Wassen op 40°.</DescriptionCatalogue><DescriptionCatalogue locale="sv">Fast linning med hällor och knytband. Framfickor. Fickor fram och bak med knapp. Slejf för justerbar längd. Mjuk, tvättad kvalitet. Tvätt 40°.</DescriptionCatalogue></DescriptionCatalogues><Animal_Origin>false</Animal_Origin><MeasureHeading cvl="MeasureHeading"><value><![CDATA[Length]]></value><value><![CDATA[Size]]></value></MeasureHeading><MeasurementDescriptions><MeasurementDescription locale="da" /><MeasurementDescription locale="de_CH" /><MeasurementDescription locale="en" /><MeasurementDescription locale="de" /><MeasurementDescription locale="nl" /><MeasurementDescription locale="sv" /></MeasurementDescriptions><Program cvl="Program"><![CDATA[D]]></Program><IsLive /><Composition cvl="Composition"><![CDATA[10]]></Composition><ProductMainGroup cvl="ProductMainGroup"><![CDATA[09]]></ProductMainGroup><SizeGuide /><SizeGroupName><![CDATA[N_L_34-54]]></SizeGroupName><MeasurementImage /><ProductStatus cvl="ProductStatus" /><translationReady /><Season cvl="Season"><value><![CDATA[131]]></value></Season><Concept cvl="Concept"><![CDATA[B]]></Concept><DisplaySize>true</DisplaySize><MeasureChartAbrv><![CDATA[S]]></MeasureChartAbrv><ProductSubGroup cvl="ProductSubGroup" /><LengthDescription cvl="LengthDescription"><![CDATA[MES09]]></LengthDescription><ProductGroup cvl="ProductGroup"><![CDATA[0900]]></ProductGroup><DescriptionWebs><DescriptionWeb locale="da" /><DescriptionWeb locale="de_CH" /><DescriptionWeb locale="en" /><DescriptionWeb locale="de" /><DescriptionWeb locale="nl" /><DescriptionWeb locale="sv" /></DescriptionWebs><HeaderWebs><HeaderWeb locale="da">Hørbukser</HeaderWeb><HeaderWeb locale="de_CH">Leinenhose</HeaderWeb><HeaderWeb locale="en">Linen trousers</HeaderWeb><HeaderWeb locale="de">Leinenhose</HeaderWeb><HeaderWeb locale="nl">Linnen broek</HeaderWeb><HeaderWeb locale="sv">Linnebyxor</HeaderWeb></HeaderWebs><CompositionFoders><CompositionFoder locale="da" /><CompositionFoder locale="de_CH" /><CompositionFoder locale="en" /><CompositionFoder locale="de" /><CompositionFoder locale="nl" /><CompositionFoder locale="sv" /></CompositionFoders><DescriptionPDMs><DescriptionPDM locale="da">Sgr: trousers in linen. Shell fabric/Yderstof/Oberstoff 100% Linen/Hør/Leinen Vask 40°</DescriptionPDM><DescriptionPDM locale="de_CH" /><DescriptionPDM locale="en" /><DescriptionPDM locale="de" /><DescriptionPDM locale="nl" /><DescriptionPDM locale="sv" /></DescriptionPDMs><usedInSpread /><LengthImage /><DisplayComposition>true</DisplayComposition><StyleNbr><![CDATA[7210]]></StyleNbr><HeaderPDMs><HeaderPDM locale="da">Hørbuks</HeaderPDM><HeaderPDM locale="de_CH" /><HeaderPDM locale="en" /><HeaderPDM locale="de" /><HeaderPDM locale="nl" /><HeaderPDM locale="sv" /></HeaderPDMs><Items><Item id="134512436014476297"><Descriptions><Description locale="da" /><Description locale="de_CH" /><Description locale="en" /><Description locale="de" /><Description locale="nl" /><Description locale="sv" /></Descriptions><AdCodes><![CDATA[<AdCode catalogue="2013-FAV-PSPR">F</AdCode><AdCode catalogue="2013-BAP-SUM">3</AdCode><AdCode catalogue="2013-BAP-PSPR">1</AdCode>]]></AdCodes><CinoNumber><![CDATA[58232]]></CinoNumber><Prices><![CDATA[<Catalogue name="2013-FAV-PSPR"><Country code="DK" currency="DKK"><Size name="L34">469.95</Size><Size name="L36">469.95</Size><Size name="L38">469.95</Size><Size name="L40">469.95</Size><Size name="L42">469.95</Size><Size name="L44">469.95</Size><Size name="L46">469.95</Size><Size name="L48">469.95</Size><Size name="L50">469.95</Size><Size name="L52">469.95</Size><Size name="L54">469.95</Size></Country><Country code="SE" currency="SEK"><Size name="L34">599.95</Size><Size name="L36">599.95</Size><Size name="L38">599.95</Size><Size name="L40">599.95</Size><Size name="L42">599.95</Size><Size name="L44">599.95</Size><Size name="L46">599.95</Size><Size name="L48">599.95</Size><Size name="L50">599.95</Size><Size name="L52">599.95</Size><Size name="L54">599.95</Size></Country><Country code="NL" currency="EUR"><Size name="L34">73.95</Size><Size name="L36">73.95</Size><Size name="L38">73.95</Size><Size name="L40">73.95</Size><Size name="L42">73.95</Size><Size name="L44">73.95</Size><Size name="L46">73.95</Size><Size name="L48">73.95</Size><Size name="L50">73.95</Size><Size name="L52">73.95</Size><Size name="L54">73.95</Size></Country><Country code="DE" currency="EUR"><Size name="L34">74.95</Size><Size name="L36">74.95</Size><Size name="L38">74.95</Size><Size name="L40">74.95</Size><Size name="L42">74.95</Size><Size name="L44">74.95</Size><Size name="L46">74.95</Size><Size name="L48">74.95</Size><Size name="L50">74.95</Size><Size name="L52">74.95</Size><Size name="L54">74.95</Size></Country><Country code="CH" currency="SFR"><Size name="L34">139.95</Size><Size name="L36">139.95</Size><Size name="L38">139.95</Size><Size name="L40">139.95</Size><Size name="L42">139.95</Size><Size name="L44">139.95</Size><Size name="L46">139.95</Size><Size name="L48">139.95</Size><Size name="L50">139.95</Size><Size name="L52">139.95</Size><Size name="L54">139.95</Size></Country><Country code="GB" currency="GBP"><Size name="8">57.00</Size><Size name="10">57.00</Size><Size name="12">57.00</Size><Size name="14">57.00</Size><Size name="16">57.00</Size><Size name="18">57.00</Size><Size name="20">57.00</Size><Size name="22">57.00</Size><Size name="24">57.00</Size><Size name="26">57.00</Size><Size name="28">57.00</Size></Country></Catalogue><Catalogue name="2013-BAP-SUM"><Country code="DK" currency="DKK"><Size name="L34">469.95</Size><Size name="L36">469.95</Size><Size name="L38">469.95</Size><Size name="L40">469.95</Size><Size name="L42">469.95</Size><Size name="L44">469.95</Size><Size name="L46">469.95</Size><Size name="L48">469.95</Size><Size name="L50">469.95</Size><Size name="L52">469.95</Size><Size name="L54">469.95</Size></Country><Country code="SE" currency="SEK"><Size name="L34">599.95</Size><Size name="L36">599.95</Size><Size name="L38">599.95</Size><Size name="L40">599.95</Size><Size name="L42">599.95</Size><Size name="L44">599.95</Size><Size name="L46">599.95</Size><Size name="L48">599.95</Size><Size name="L50">599.95</Size><Size name="L52">599.95</Size><Size name="L54">599.95</Size></Country><Country code="NL" currency="EUR"><Size name="L34">73.95</Size><Size name="L36">73.95</Size><Size name="L38">73.95</Size><Size name="L40">73.95</Size><Size name="L42">73.95</Size><Size name="L44">73.95</Size><Size name="L46">73.95</Size><Size name="L48">73.95</Size><Size name="L50">73.95</Size><Size name="L52">73.95</Size><Size name="L54">73.95</Size></Country><Country code="DE" currency="EUR"><Size name="L34">74.95</Size><Size name="L36">74.95</Size><Size name="L38">74.95</Size><Size name="L40">74.95</Size><Size name="L42">74.95</Size><Size name="L44">74.95</Size><Size name="L46">74.95</Size><Size name="L48">74.95</Size><Size name="L50">74.95</Size><Size name="L52">74.95</Size><Size name="L54">74.95</Size></Country><Country code="CH" currency="SFR"><Size name="L34">139.95</Size><Size name="L36">139.95</Size><Size name="L38">139.95</Size><Size name="L40">139.95</Size><Size name="L42">139.95</Size><Size name="L44">139.95</Size><Size name="L46">139.95</Size><Size name="L48">139.95</Size><Size name="L50">139.95</Size><Size name="L52">139.95</Size><Size name="L54">139.95</Size></Country><Country code="GB" currency="GBP"><Size name="8">57.00</Size><Size name="10">57.00</Size><Size name="12">57.00</Size><Size name="14">57.00</Size><Size name="16">57.00</Size><Size name="18">57.00</Size><Size name="20">57.00</Size><Size name="22">57.00</Size><Size name="24">57.00</Size><Size name="26">57.00</Size><Size name="28">57.00</Size></Country></Catalogue><Catalogue name="2013-BAP-PSPR"><Country code="DK" currency="DKK"><Size name="L34">469.95</Size><Size name="L36">469.95</Size><Size name="L38">469.95</Size><Size name="L40">469.95</Size><Size name="L42">469.95</Size><Size name="L44">469.95</Size><Size name="L46">469.95</Size><Size name="L48">469.95</Size><Size name="L50">469.95</Size><Size name="L52">469.95</Size><Size name="L54">469.95</Size></Country><Country code="SE" currency="SEK"><Size name="L34">599.95</Size><Size name="L36">599.95</Size><Size name="L38">599.95</Size><Size name="L40">599.95</Size><Size name="L42">599.95</Size><Size name="L44">599.95</Size><Size name="L46">599.95</Size><Size name="L48">599.95</Size><Size name="L50">599.95</Size><Size name="L52">599.95</Size><Size name="L54">599.95</Size></Country><Country code="NL" currency="EUR"><Size name="L34">73.95</Size><Size name="L36">73.95</Size><Size name="L38">73.95</Size><Size name="L40">73.95</Size><Size name="L42">73.95</Size><Size name="L44">73.95</Size><Size name="L46">73.95</Size><Size name="L48">73.95</Size><Size name="L50">73.95</Size><Size name="L52">73.95</Size><Size name="L54">73.95</Size></Country><Country code="DE" currency="EUR"><Size name="L34">74.95</Size><Size name="L36">74.95</Size><Size name="L38">74.95</Size><Size name="L40">74.95</Size><Size name="L42">74.95</Size><Size name="L44">74.95</Size><Size name="L46">74.95</Size><Size name="L48">74.95</Size><Size name="L50">74.95</Size><Size name="L52">74.95</Size><Size name="L54">74.95</Size></Country><Country code="CH" currency="SFR"><Size name="L34">139.95</Size><Size name="L36">139.95</Size><Size name="L38">139.95</Size><Size name="L40">139.95</Size><Size name="L42">139.95</Size><Size name="L44">139.95</Size><Size name="L46">139.95</Size><Size name="L48">139.95</Size><Size name="L50">139.95</Size><Size name="L52">139.95</Size><Size name="L54">139.95</Size></Country><Country code="GB" currency="GBP"><Size name="8">57.00</Size><Size name="10">57.00</Size><Size name="12">57.00</Size><Size name="14">57.00</Size><Size name="16">57.00</Size><Size name="18">57.00</Size><Size name="20">57.00</Size><Size name="22">57.00</Size><Size name="24">57.00</Size><Size name="26">57.00</Size><Size name="28">57.00</Size></Country></Catalogue>]]></Prices><Portals><Portal locale="da" /><Portal locale="de_CH" /><Portal locale="en" /><Portal locale="de" /><Portal locale="nl" /><Portal locale="sv" /></Portals><WashTemperature cvl="WashIcon" /><Inspirations><Inspiration locale="da" /><Inspiration locale="de_CH" /><Inspiration locale="en" /><Inspiration locale="de" /><Inspiration locale="nl" /><Inspiration locale="sv" /></Inspirations><Color cvl="Color"><![CDATA[0001]]></Color><ProductSubGroup /><Sizess><Sizes locale="da">L34-L36-L38-L40-L42-L44-L46-L48-L50-L52-L54</Sizes><Sizes locale="de_CH">L34-L36-L38-L40-L42-L44-L46-L48-L50-L52-L54</Sizes><Sizes locale="en">L34-L36-L38-L40-L42-L44-L46-L48-L50-L52-L54</Sizes><Sizes locale="de">L34-L36-L38-L40-L42-L44-L46-L48-L50-L52-L54</Sizes><Sizes locale="nl">L34-L36-L38-L40-L42-L44-L46-L48-L50-L52-L54</Sizes><Sizes locale="sv">L34-L36-L38-L40-L42-L44-L46-L48-L50-L52-L54</Sizes></Sizess><WashIcon cvl="WashIcon"><value><![CDATA[10700]]></value><value><![CDATA[20100]]></value><value><![CDATA[50150]]></value><value><![CDATA[30400]]></value><value><![CDATA[40500]]></value></WashIcon><ColorGroup><![CDATA[White]]></ColorGroup><MeasurementChart><![CDATA[<Measure name="1/2 Waist/-band width" description="1/2 Waist/-band width"><Size name="L34">37.00</Size><Size name="L36">38.50</Size><Size name="L38">40.00</Size><Size name="L40">42.00</Size><Size name="L42">44.50</Size><Size name="L44">47.50</Size><Size name="L46">50.50</Size><Size name="L48">53.50</Size><Size name="L50">56.50</Size><Size name="L52">59.50</Size><Size name="L54">63.00</Size></Measure><Measure name="Hip depth, front middle" description="Hip depth, front middle"><Size name="L34">13.00</Size><Size name="L36">13.50</Size><Size name="L38">14.00</Size><Size name="L40">14.50</Size><Size name="L42">15.00</Size><Size name="L44">15.70</Size><Size name="L46">16.40</Size><Size name="L48">17.10</Size><Size name="L50">17.80</Size><Size name="L52">18.50</Size><Size name="L54">19.50</Size></Measure><Measure name="1/2 Hip width" description="1/2 Hip width"><Size name="L34">49.50</Size><Size name="L36">51.00</Size><Size name="L38">52.50</Size><Size name="L40">54.50</Size><Size name="L42">56.50</Size><Size name="L44">59.20</Size><Size name="L46">61.90</Size><Size name="L48">64.60</Size><Size name="L50">67.30</Size><Size name="L52">70.00</Size><Size name="L54">73.00</Size></Measure><Measure name="1/2 Thigh width" description="1/2 Thigh width"><Size name="L34">29.70</Size><Size name="L36">30.60</Size><Size name="L38">31.50</Size><Size name="L40">32.75</Size><Size name="L42">34.00</Size><Size name="L44">35.70</Size><Size name="L46">37.40</Size><Size name="L48">39.10</Size><Size name="L50">40.80</Size><Size name="L52">42.50</Size><Size name="L54">44.80</Size></Measure><Measure name="Knee height" description="Knee height"><Size name="L34">37.00</Size><Size name="L36">37.00</Size><Size name="L38">37.00</Size><Size name="L40">37.00</Size><Size name="L42">37.00</Size><Size name="L44">37.00</Size><Size name="L46">37.00</Size><Size name="L48">37.00</Size><Size name="L50">37.00</Size><Size name="L52">37.00</Size><Size name="L54">37.00</Size></Measure><Measure name="1/2 Knee width" description="1/2 Knee width"><Size name="L34">22.50</Size><Size name="L36">23.25</Size><Size name="L38">24.00</Size><Size name="L40">24.75</Size><Size name="L42">25.50</Size><Size name="L44">26.50</Size><Size name="L46">27.50</Size><Size name="L48">28.50</Size><Size name="L50">29.50</Size><Size name="L52">30.50</Size><Size name="L54">31.80</Size></Measure><Measure name="1/2 Width of trousers' hem" description="1/2 Width of trousers' hem"><Size name="L34">23.00</Size><Size name="L36">23.50</Size><Size name="L38">24.00</Size><Size name="L40">24.50</Size><Size name="L42">25.00</Size><Size name="L44">25.80</Size><Size name="L46">26.60</Size><Size name="L48">27.40</Size><Size name="L50">28.20</Size><Size name="L52">29.00</Size><Size name="L54">30.00</Size></Measure><Measure name="Front rise excl. waistband" description="Front rise excl. waistband"><Size name="L34">17.00</Size><Size name="L36">18.00</Size><Size name="L38">19.00</Size><Size name="L40">20.00</Size><Size name="L42">21.00</Size><Size name="L44">22.00</Size><Size name="L46">24.00</Size><Size name="L48">25.00</Size><Size name="L50">26.00</Size><Size name="L52">27.00</Size><Size name="L54">28.00</Size></Measure><Measure name="Back rise excl. waistband" description="Back rise excl. waistband"><Size name="L34">30.00</Size><Size name="L36">31.00</Size><Size name="L38">32.00</Size><Size name="L40">33.00</Size><Size name="L42">34.00</Size><Size name="L44">35.60</Size><Size name="L46">38.60</Size><Size name="L48">40.20</Size><Size name="L50">41.80</Size><Size name="L52">43.40</Size><Size name="L54">45.40</Size></Measure><Measure name="Inseam length" description="Inseam length"><Size name="L34">86.00</Size><Size name="L36">86.00</Size><Size name="L38">86.00</Size><Size name="L40">86.00</Size><Size name="L42">86.00</Size><Size name="L44">86.00</Size><Size name="L46">86.00</Size><Size name="L48">86.00</Size><Size name="L50">86.00</Size><Size name="L52">86.00</Size><Size name="L54">86.00</Size></Measure><Measure name="Distance between pockets" description="Distance between pockets"><Size name="L34">9.00</Size><Size name="L36">9.00</Size><Size name="L38">9.00</Size><Size name="L40">11.00</Size><Size name="L42">11.00</Size><Size name="L44">13.00</Size><Size name="L46">13.00</Size><Size name="L48">15.00</Size><Size name="L50">15.00</Size><Size name="L52">17.00</Size><Size name="L54">17.00</Size></Measure><Measure name="Belt loop breadth" description="Belt loop breadth"><Size name="L34">1.20</Size><Size name="L36">1.20</Size><Size name="L38">1.20</Size><Size name="L40">1.20</Size><Size name="L42">1.20</Size><Size name="L44">1.20</Size><Size name="L46">1.20</Size><Size name="L48">1.20</Size><Size name="L50">1.20</Size><Size name="L52">1.20</Size><Size name="L54">1.20</Size></Measure><Measure name="Belt loop length" description="Belt loop length"><Size name="L34">5.50</Size><Size name="L36">5.50</Size><Size name="L38">5.50</Size><Size name="L40">5.50</Size><Size name="L42">5.50</Size><Size name="L44">5.50</Size><Size name="L46">5.50</Size><Size name="L48">5.50</Size><Size name="L50">5.50</Size><Size name="L52">5.50</Size><Size name="L54">5.50</Size></Measure><Measure name="Buttons incl. 1 extra button" description="Buttons incl. 1 extra button"><Size name="L34">8.00</Size><Size name="L36">8.00</Size><Size name="L38">8.00</Size><Size name="L40">8.00</Size><Size name="L42">8.00</Size><Size name="L44">8.00</Size><Size name="L46">8.00</Size><Size name="L48">8.00</Size><Size name="L50">8.00</Size><Size name="L52">8.00</Size><Size name="L54">8.00</Size></Measure><Measure name="Zipper top stitching" description="Zipper top stitching"><Size name="L34">11.00</Size><Size name="L36">11.00</Size><Size name="L38">12.00</Size><Size name="L40">12.00</Size><Size name="L42">13.00</Size><Size name="L44">13.00</Size><Size name="L46">14.00</Size><Size name="L48">14.00</Size><Size name="L50">15.00</Size><Size name="L52">15.00</Size><Size name="L54">15.00</Size></Measure><Measure name="Waistb. breadth" description="Waistb. breadth"><Size name="L34">4.50</Size><Size name="L36">4.50</Size><Size name="L38">4.50</Size><Size name="L40">4.50</Size><Size name="L42">4.50</Size><Size name="L44">4.50</Size><Size name="L46">4.50</Size><Size name="L48">4.50</Size><Size name="L50">4.50</Size><Size name="L52">4.50</Size><Size name="L54">4.50</Size></Measure><Measure name="Inseam folded up" description="Inseam folded up"><Size name="L34">55.00</Size><Size name="L36">55.00</Size><Size name="L38">55.00</Size><Size name="L40">55.00</Size><Size name="L42">55.00</Size><Size name="L44">55.00</Size><Size name="L46">55.00</Size><Size name="L48">55.00</Size><Size name="L50">55.00</Size><Size name="L52">55.00</Size><Size name="L54">55.00</Size></Measure><Measure name="Strap breath_1" description="Strap breath_1"><Size name="L34">3.00</Size><Size name="L36">3.00</Size><Size name="L38">3.00</Size><Size name="L40">3.00</Size><Size name="L42">3.00</Size><Size name="L44">3.00</Size><Size name="L46">3.00</Size><Size name="L48">3.00</Size><Size name="L50">3.00</Size><Size name="L52">3.00</Size><Size name="L54">3.00</Size></Measure>]]></MeasurementChart><Length><![CDATA[86.00]]></Length><ActiveCatalogue cvl="Catalogue"><value><![CDATA[2013-FAV-PSPR]]></value><value><![CDATA[2013-BAP-SUM]]></value><value><![CDATA[2013-BAP-PSPR]]></value></ActiveCatalogue><LengthChart><![CDATA[<Size name="L34">86.00</Size><Size name="L36">86.00</Size><Size name="L38">86.00</Size><Size name="L40">86.00</Size><Size name="L42">86.00</Size><Size name="L44">86.00</Size><Size name="L46">86.00</Size><Size name="L48">86.00</Size><Size name="L50">86.00</Size><Size name="L52">86.00</Size><Size name="L54">86.00</Size>]]></LengthChart><WashInstructions><WashInstruction locale="da">Vaskes med vrangen ud med lignende farver. Undlad iblødsætning. Strækkes i facon i våd tilstand. Hængetørring. Stryges på bagsiden. Krymp 1-3%</WashInstruction><WashInstruction locale="de_CH">Von links waschen mit ähnlichen Farben. Nicht einweichen. In nassem Zustand in Form ziehen. Hängend trocknen. Von links bügeln. Läuft ein 1-3%</WashInstruction><WashInstruction locale="en">Wash inside out with similar colours. No soaking. To be stretched in shape while wet. Hang dry. Iron on backside. Shrink 1-3%</WashInstruction><WashInstruction locale="de">Von links waschen mit ähnlichen Farben. Nicht einweichen. In nassem Zustand in Form ziehen. Hängend trocknen. Von links bügeln. Läuft ein 1-3%</WashInstruction><WashInstruction locale="nl">Binnenste buiten wassen met dezelfde kleuren. Niet weken. In vochtige toestand, voorzichtig op maat rekken. Hangend drogen. Binnenste buiten strijken. Krimp: 1 - 3%.</WashInstruction><WashInstruction locale="sv">Tvättas med avigsidan ut med liknande färger. Undvik blötläggning. Sträcks försiktigt i vått tillstånd. Ska hängtorka. Strykes på baksidan. Krymper: 1 - 3%.</WashInstruction></WashInstructions><IsLive /><LeadPicture><Resource id="134666460816199322_62805" /></LeadPicture><Resources><Resource id="134666460816199322_62805"><OriginalFilename><![CDATA[13102_007210_03_A_0001.jpg]]></OriginalFilename><Year cvl="Year"><![CDATA[13]]></Year><PDMIdentifier /><CatalogAdcode cvl="CatalogAdcode"><value><![CDATA[2013-BAP-PSPR]]></value><value><![CDATA[2013-BAP-SUM]]></value><value><![CDATA[2013-BAP-PAUT]]></value><value><![CDATA[2013-FAV-PSPR]]></value><value><![CDATA[2013-FAV2-SUM]]></value><value><![CDATA[2013-BAP-SPR]]></value><value><![CDATA[2013-PLUS-PSPR]]></value><value><![CDATA[2013-UDS1-SUM]]></value></CatalogAdcode><ImageType cvl="ImageType"><![CDATA[packshots]]></ImageType><ResourceFileId><![CDATA[62805]]></ResourceFileId><MimeType><![CDATA[image/jpeg]]></MimeType><Season cvl="Season"><![CDATA[131]]></Season><AltTexts><AltText locale="da" /><AltText locale="de_CH" /><AltText locale="en" /><AltText locale="de" /><AltText locale="nl" /><AltText locale="sv" /></AltTexts><Filename>D:/inRiver/Publish/Production/Pics/134666460816199322_62805.jpg</Filename></Resource><Resource id="134666460969222388_59402"><OriginalFilename><![CDATA[13102_007210_03_B_0001.jpg]]></OriginalFilename><Year cvl="Year"><![CDATA[13]]></Year><PDMIdentifier /><CatalogAdcode cvl="CatalogAdcode"><value><![CDATA[2013-BAP-PAUT]]></value><value><![CDATA[2013-BAP-PSPR]]></value><value><![CDATA[2013-PLUS-PSPR]]></value><value><![CDATA[2013-FAV-PSPR]]></value><value><![CDATA[2013-BAP-SPR]]></value><value><![CDATA[2013-FAV2-SUM]]></value></CatalogAdcode><ImageType cvl="ImageType"><![CDATA[packshots]]></ImageType><ResourceFileId><![CDATA[59402]]></ResourceFileId><MimeType><![CDATA[image/jpeg]]></MimeType><Season cvl="Season"><![CDATA[131]]></Season><AltTexts><AltText locale="da" /><AltText locale="de_CH" /><AltText locale="en" /><AltText locale="de" /><AltText locale="nl" /><AltText locale="sv" /></AltTexts><Filename>D:/inRiver/Publish/Production/Pics/134666460969222388_59402.jpg</Filename></Resource><Resource id="134812355048377291_50073"><OriginalFilename><![CDATA[131B_21_03_V120.jpg]]></OriginalFilename><Year cvl="Year"><![CDATA[13]]></Year><PDMIdentifier /><CatalogAdcode cvl="CatalogAdcode"><value><![CDATA[2013-BAP-PSPR]]></value><value><![CDATA[2013-BAP-SUM]]></value><value><![CDATA[2013-FAV-PSPR]]></value></CatalogAdcode><ImageType cvl="ImageType"><![CDATA[modelshots]]></ImageType><ResourceFileId><![CDATA[50073]]></ResourceFileId><MimeType><![CDATA[image/jpeg]]></MimeType><Season cvl="Season"><![CDATA[131]]></Season><AltTexts><AltText locale="da" /><AltText locale="de_CH" /><AltText locale="en" /><AltText locale="de" /><AltText locale="nl" /><AltText locale="sv" /></AltTexts><Filename>D:/inRiver/Publish/Production/Pics/134812355048377291_50073.jpg</Filename></Resource></Resources></Item><Item id="134512435992538885"><Descriptions><Description locale="da" /><Description locale="de_CH" /><Description locale="en" /><Description locale="de" /><Description locale="nl" /><Description locale="sv" /></Descriptions><AdCodes><![CDATA[<AdCode catalogue="2013-FAV-PSPR">F</AdCode><AdCode catalogue="2013-BAP-SUM">3</AdCode><AdCode catalogue="2013-BAP-PSPR">1</AdCode>]]></AdCodes><CinoNumber><![CDATA[58231]]></CinoNumber><Prices><![CDATA[<Catalogue name="2013-FAV-PSPR"><Country code="DK" currency="DKK"><Size name="N34">469.95</Size><Size name="N36">469.95</Size><Size name="N38">469.95</Size><Size name="N40">469.95</Size><Size name="N42">469.95</Size><Size name="N44">469.95</Size><Size name="N46">469.95</Size><Size name="N48">469.95</Size><Size name="N50">469.95</Size><Size name="N52">469.95</Size><Size name="N54">469.95</Size></Country><Country code="SE" currency="SEK"><Size name="N34">599.95</Size><Size name="N36">599.95</Size><Size name="N38">599.95</Size><Size name="N40">599.95</Size><Size name="N42">599.95</Size><Size name="N44">599.95</Size><Size name="N46">599.95</Size><Size name="N48">599.95</Size><Size name="N50">599.95</Size><Size name="N52">599.95</Size><Size name="N54">599.95</Size></Country><Country code="NL" currency="EUR"><Size name="N34">73.95</Size><Size name="N36">73.95</Size><Size name="N38">73.95</Size><Size name="N40">73.95</Size><Size name="N42">73.95</Size><Size name="N44">73.95</Size><Size name="N46">73.95</Size><Size name="N48">73.95</Size><Size name="N50">73.95</Size><Size name="N52">73.95</Size><Size name="N54">73.95</Size></Country><Country code="DE" currency="EUR"><Size name="N34">74.95</Size><Size name="N36">74.95</Size><Size name="N38">74.95</Size><Size name="N40">74.95</Size><Size name="N42">74.95</Size><Size name="N44">74.95</Size><Size name="N46">74.95</Size><Size name="N48">74.95</Size><Size name="N50">74.95</Size><Size name="N52">74.95</Size><Size name="N54">74.95</Size></Country><Country code="CH" currency="SFR"><Size name="N34">139.95</Size><Size name="N36">139.95</Size><Size name="N38">139.95</Size><Size name="N40">139.95</Size><Size name="N42">139.95</Size><Size name="N44">139.95</Size><Size name="N46">139.95</Size><Size name="N48">139.95</Size><Size name="N50">139.95</Size><Size name="N52">139.95</Size><Size name="N54">139.95</Size></Country><Country code="GB" currency="GBP"><Size name="8">57.00</Size><Size name="10">57.00</Size><Size name="12">57.00</Size><Size name="14">57.00</Size><Size name="16">57.00</Size><Size name="18">57.00</Size><Size name="20">57.00</Size><Size name="22">57.00</Size><Size name="24">57.00</Size><Size name="26">57.00</Size><Size name="28">57.00</Size></Country></Catalogue><Catalogue name="2013-BAP-SUM"><Country code="DK" currency="DKK"><Size name="N34">469.95</Size><Size name="N36">469.95</Size><Size name="N38">469.95</Size><Size name="N40">469.95</Size><Size name="N42">469.95</Size><Size name="N44">469.95</Size><Size name="N46">469.95</Size><Size name="N48">469.95</Size><Size name="N50">469.95</Size><Size name="N52">469.95</Size><Size name="N54">469.95</Size></Country><Country code="SE" currency="SEK"><Size name="N34">599.95</Size><Size name="N36">599.95</Size><Size name="N38">599.95</Size><Size name="N40">599.95</Size><Size name="N42">599.95</Size><Size name="N44">599.95</Size><Size name="N46">599.95</Size><Size name="N48">599.95</Size><Size name="N50">599.95</Size><Size name="N52">599.95</Size><Size name="N54">599.95</Size></Country><Country code="NL" currency="EUR"><Size name="N34">73.95</Size><Size name="N36">73.95</Size><Size name="N38">73.95</Size><Size name="N40">73.95</Size><Size name="N42">73.95</Size><Size name="N44">73.95</Size><Size name="N46">73.95</Size><Size name="N48">73.95</Size><Size name="N50">73.95</Size><Size name="N52">73.95</Size><Size name="N54">73.95</Size></Country><Country code="DE" currency="EUR"><Size name="N34">74.95</Size><Size name="N36">74.95</Size><Size name="N38">74.95</Size><Size name="N40">74.95</Size><Size name="N42">74.95</Size><Size name="N44">74.95</Size><Size name="N46">74.95</Size><Size name="N48">74.95</Size><Size name="N50">74.95</Size><Size name="N52">74.95</Size><Size name="N54">74.95</Size></Country><Country code="CH" currency="SFR"><Size name="N34">139.95</Size><Size name="N36">139.95</Size><Size name="N38">139.95</Size><Size name="N40">139.95</Size><Size name="N42">139.95</Size><Size name="N44">139.95</Size><Size name="N46">139.95</Size><Size name="N48">139.95</Size><Size name="N50">139.95</Size><Size name="N52">139.95</Size><Size name="N54">139.95</Size></Country><Country code="GB" currency="GBP"><Size name="8">57.00</Size><Size name="10">57.00</Size><Size name="12">57.00</Size><Size name="14">57.00</Size><Size name="16">57.00</Size><Size name="18">57.00</Size><Size name="20">57.00</Size><Size name="22">57.00</Size><Size name="24">57.00</Size><Size name="26">57.00</Size><Size name="28">57.00</Size></Country></Catalogue><Catalogue name="2013-BAP-PSPR"><Country code="DK" currency="DKK"><Size name="N34">469.95</Size><Size name="N36">469.95</Size><Size name="N38">469.95</Size><Size name="N40">469.95</Size><Size name="N42">469.95</Size><Size name="N44">469.95</Size><Size name="N46">469.95</Size><Size name="N48">469.95</Size><Size name="N50">469.95</Size><Size name="N52">469.95</Size><Size name="N54">469.95</Size></Country><Country code="SE" currency="SEK"><Size name="N34">599.95</Size><Size name="N36">599.95</Size><Size name="N38">599.95</Size><Size name="N40">599.95</Size><Size name="N42">599.95</Size><Size name="N44">599.95</Size><Size name="N46">599.95</Size><Size name="N48">599.95</Size><Size name="N50">599.95</Size><Size name="N52">599.95</Size><Size name="N54">599.95</Size></Country><Country code="NL" currency="EUR"><Size name="N34">73.95</Size><Size name="N36">73.95</Size><Size name="N38">73.95</Size><Size name="N40">73.95</Size><Size name="N42">73.95</Size><Size name="N44">73.95</Size><Size name="N46">73.95</Size><Size name="N48">73.95</Size><Size name="N50">73.95</Size><Size name="N52">73.95</Size><Size name="N54">73.95</Size></Country><Country code="DE" currency="EUR"><Size name="N34">74.95</Size><Size name="N36">74.95</Size><Size name="N38">74.95</Size><Size name="N40">74.95</Size><Size name="N42">74.95</Size><Size name="N44">74.95</Size><Size name="N46">74.95</Size><Size name="N48">74.95</Size><Size name="N50">74.95</Size><Size name="N52">74.95</Size><Size name="N54">74.95</Size></Country><Country code="CH" currency="SFR"><Size name="N34">139.95</Size><Size name="N36">139.95</Size><Size name="N38">139.95</Size><Size name="N40">139.95</Size><Size name="N42">139.95</Size><Size name="N44">139.95</Size><Size name="N46">139.95</Size><Size name="N48">139.95</Size><Size name="N50">139.95</Size><Size name="N52">139.95</Size><Size name="N54">139.95</Size></Country><Country code="GB" currency="GBP"><Size name="8">57.00</Size><Size name="10">57.00</Size><Size name="12">57.00</Size><Size name="14">57.00</Size><Size name="16">57.00</Size><Size name="18">57.00</Size><Size name="20">57.00</Size><Size name="22">57.00</Size><Size name="24">57.00</Size><Size name="26">57.00</Size><Size name="28">57.00</Size></Country></Catalogue>]]></Prices><Portals><Portal locale="da" /><Portal locale="de_CH" /><Portal locale="en" /><Portal locale="de" /><Portal locale="nl" /><Portal locale="sv" /></Portals><WashTemperature cvl="WashIcon" /><Inspirations><Inspiration locale="da" /><Inspiration locale="de_CH" /><Inspiration locale="en" /><Inspiration locale="de" /><Inspiration locale="nl" /><Inspiration locale="sv" /></Inspirations><Color cvl="Color"><![CDATA[0001]]></Color><ProductSubGroup /><Sizess><Sizes locale="da">N34-N36-N38-N40-N42-N44-N46-N48-N50-N52-N54</Sizes><Sizes locale="de_CH">N34-N36-N38-N40-N42-N44-N46-N48-N50-N52-N54</Sizes><Sizes locale="en">N34-N36-N38-N40-N42-N44-N46-N48-N50-N52-N54</Sizes><Sizes locale="de">N34-N36-N38-N40-N42-N44-N46-N48-N50-N52-N54</Sizes><Sizes locale="nl">N34-N36-N38-N40-N42-N44-N46-N48-N50-N52-N54</Sizes><Sizes locale="sv">N34-N36-N38-N40-N42-N44-N46-N48-N50-N52-N54</Sizes></Sizess><WashIcon cvl="WashIcon"><value><![CDATA[10700]]></value><value><![CDATA[20100]]></value><value><![CDATA[50150]]></value><value><![CDATA[30400]]></value><value><![CDATA[40500]]></value></WashIcon><ColorGroup><![CDATA[White]]></ColorGroup><MeasurementChart><![CDATA[<Measure name="1/2 Waist/-band width" description="1/2 Waist/-band width"><Size name="N34">37.00</Size><Size name="N36">38.50</Size><Size name="N38">40.00</Size><Size name="N40">42.00</Size><Size name="N42">44.50</Size><Size name="N44">47.50</Size><Size name="N46">50.50</Size><Size name="N48">53.50</Size><Size name="N50">56.50</Size><Size name="N52">59.50</Size><Size name="N54">63.00</Size></Measure><Measure name="Hip depth, front middle" description="Hip depth, front middle"><Size name="N34">13.00</Size><Size name="N36">13.50</Size><Size name="N38">14.00</Size><Size name="N40">14.50</Size><Size name="N42">15.00</Size><Size name="N44">15.70</Size><Size name="N46">16.40</Size><Size name="N48">17.10</Size><Size name="N50">17.80</Size><Size name="N52">18.50</Size><Size name="N54">19.50</Size></Measure><Measure name="1/2 Hip width" description="1/2 Hip width"><Size name="N34">49.50</Size><Size name="N36">51.00</Size><Size name="N38">52.50</Size><Size name="N40">54.50</Size><Size name="N42">56.50</Size><Size name="N44">59.20</Size><Size name="N46">61.90</Size><Size name="N48">64.60</Size><Size name="N50">67.30</Size><Size name="N52">70.00</Size><Size name="N54">73.00</Size></Measure><Measure name="1/2 Thigh width" description="1/2 Thigh width"><Size name="N34">29.70</Size><Size name="N36">30.60</Size><Size name="N38">31.50</Size><Size name="N40">32.75</Size><Size name="N42">34.00</Size><Size name="N44">35.70</Size><Size name="N46">37.40</Size><Size name="N48">39.10</Size><Size name="N50">40.80</Size><Size name="N52">42.50</Size><Size name="N54">44.80</Size></Measure><Measure name="Knee height" description="Knee height"><Size name="N34">34.00</Size><Size name="N36">34.00</Size><Size name="N38">34.00</Size><Size name="N40">34.00</Size><Size name="N42">34.00</Size><Size name="N44">34.00</Size><Size name="N46">34.00</Size><Size name="N48">34.00</Size><Size name="N50">34.00</Size><Size name="N52">34.00</Size><Size name="N54">34.00</Size></Measure><Measure name="1/2 Knee width" description="1/2 Knee width"><Size name="N34">22.50</Size><Size name="N36">23.25</Size><Size name="N38">24.00</Size><Size name="N40">24.75</Size><Size name="N42">25.50</Size><Size name="N44">26.50</Size><Size name="N46">27.50</Size><Size name="N48">28.50</Size><Size name="N50">29.50</Size><Size name="N52">30.50</Size><Size name="N54">31.80</Size></Measure><Measure name="1/2 Width of trousers' hem" description="1/2 Width of trousers' hem"><Size name="N34">23.00</Size><Size name="N36">23.50</Size><Size name="N38">24.00</Size><Size name="N40">24.50</Size><Size name="N42">25.00</Size><Size name="N44">25.80</Size><Size name="N46">26.60</Size><Size name="N48">27.40</Size><Size name="N50">28.20</Size><Size name="N52">29.00</Size><Size name="N54">30.00</Size></Measure><Measure name="Front rise excl. waistband" description="Front rise excl. waistband"><Size name="N34">17.00</Size><Size name="N36">18.00</Size><Size name="N38">19.00</Size><Size name="N40">20.00</Size><Size name="N42">21.00</Size><Size name="N44">22.00</Size><Size name="N46">24.00</Size><Size name="N48">25.00</Size><Size name="N50">26.00</Size><Size name="N52">27.00</Size><Size name="N54">28.00</Size></Measure><Measure name="Back rise excl. waistband" description="Back rise excl. waistband"><Size name="N34">30.00</Size><Size name="N36">31.00</Size><Size name="N38">32.00</Size><Size name="N40">33.00</Size><Size name="N42">34.00</Size><Size name="N44">35.60</Size><Size name="N46">38.60</Size><Size name="N48">40.20</Size><Size name="N50">41.80</Size><Size name="N52">43.40</Size><Size name="N54">45.40</Size></Measure><Measure name="Inseam length" description="Inseam length"><Size name="N34">81.00</Size><Size name="N36">81.00</Size><Size name="N38">81.00</Size><Size name="N40">81.00</Size><Size name="N42">81.00</Size><Size name="N44">81.00</Size><Size name="N46">81.00</Size><Size name="N48">81.00</Size><Size name="N50">81.00</Size><Size name="N52">81.00</Size><Size name="N54">81.00</Size></Measure><Measure name="Distance between pockets" description="Distance between pockets"><Size name="N34">9.00</Size><Size name="N36">9.00</Size><Size name="N38">9.00</Size><Size name="N40">11.00</Size><Size name="N42">11.00</Size><Size name="N44">13.00</Size><Size name="N46">13.00</Size><Size name="N48">15.00</Size><Size name="N50">15.00</Size><Size name="N52">17.00</Size><Size name="N54">17.00</Size></Measure><Measure name="Belt loop breadth" description="Belt loop breadth"><Size name="N34">1.20</Size><Size name="N36">1.20</Size><Size name="N38">1.20</Size><Size name="N40">1.20</Size><Size name="N42">1.20</Size><Size name="N44">1.20</Size><Size name="N46">1.20</Size><Size name="N48">1.20</Size><Size name="N50">1.20</Size><Size name="N52">1.20</Size><Size name="N54">1.20</Size></Measure><Measure name="Belt loop length" description="Belt loop length"><Size name="N34">5.50</Size><Size name="N36">5.50</Size><Size name="N38">5.50</Size><Size name="N40">5.50</Size><Size name="N42">5.50</Size><Size name="N44">5.50</Size><Size name="N46">5.50</Size><Size name="N48">5.50</Size><Size name="N50">5.50</Size><Size name="N52">5.50</Size><Size name="N54">5.50</Size></Measure><Measure name="Buttons incl. 1 extra button" description="Buttons incl. 1 extra button"><Size name="N34">8.00</Size><Size name="N36">8.00</Size><Size name="N38">8.00</Size><Size name="N40">8.00</Size><Size name="N42">8.00</Size><Size name="N44">8.00</Size><Size name="N46">8.00</Size><Size name="N48">8.00</Size><Size name="N50">8.00</Size><Size name="N52">8.00</Size><Size name="N54">8.00</Size></Measure><Measure name="Zipper top stitching" description="Zipper top stitching"><Size name="N34">11.00</Size><Size name="N36">11.00</Size><Size name="N38">12.00</Size><Size name="N40">12.00</Size><Size name="N42">13.00</Size><Size name="N44">13.00</Size><Size name="N46">14.00</Size><Size name="N48">14.00</Size><Size name="N50">15.00</Size><Size name="N52">15.00</Size><Size name="N54">15.00</Size></Measure><Measure name="Waistb. breadth" description="Waistb. breadth"><Size name="N34">4.50</Size><Size name="N36">4.50</Size><Size name="N38">4.50</Size><Size name="N40">4.50</Size><Size name="N42">4.50</Size><Size name="N44">4.50</Size><Size name="N46">4.50</Size><Size name="N48">4.50</Size><Size name="N50">4.50</Size><Size name="N52">4.50</Size><Size name="N54">4.50</Size></Measure><Measure name="Inseam folded up" description="Inseam folded up"><Size name="N34">55.00</Size><Size name="N36">55.00</Size><Size name="N38">55.00</Size><Size name="N40">55.00</Size><Size name="N42">55.00</Size><Size name="N44">55.00</Size><Size name="N46">55.00</Size><Size name="N48">55.00</Size><Size name="N50">55.00</Size><Size name="N52">55.00</Size><Size name="N54">55.00</Size></Measure><Measure name="Strap breath_1" description="Strap breath_1"><Size name="N34">3.00</Size><Size name="N36">3.00</Size><Size name="N38">3.00</Size><Size name="N40">3.00</Size><Size name="N42">3.00</Size><Size name="N44">3.00</Size><Size name="N46">3.00</Size><Size name="N48">3.00</Size><Size name="N50">3.00</Size><Size name="N52">3.00</Size><Size name="N54">3.00</Size></Measure>]]></MeasurementChart><Length><![CDATA[81.00]]></Length><ActiveCatalogue cvl="Catalogue"><value><![CDATA[2013-FAV-PSPR]]></value><value><![CDATA[2013-BAP-SUM]]></value><value><![CDATA[2013-BAP-PSPR]]></value></ActiveCatalogue><LengthChart><![CDATA[<Size name="N34">81.00</Size><Size name="N36">81.00</Size><Size name="N38">81.00</Size><Size name="N40">81.00</Size><Size name="N42">81.00</Size><Size name="N44">81.00</Size><Size name="N46">81.00</Size><Size name="N48">81.00</Size><Size name="N50">81.00</Size><Size name="N52">81.00</Size><Size name="N54">81.00</Size>]]></LengthChart><WashInstructions><WashInstruction locale="da">Vaskes med vrangen ud med lignende farver. Undlad iblødsætning. Strækkes i facon i våd tilstand. Hængetørring. Stryges på bagsiden. Krymp 1-3%</WashInstruction><WashInstruction locale="de_CH">Von links waschen mit ähnlichen Farben. Nicht einweichen. In nassem Zustand in Form ziehen. Hängend trocknen. Von links bügeln. Läuft ein 1-3%</WashInstruction><WashInstruction locale="en">Wash inside out with similar colours. No soaking. To be stretched in shape while wet. Hang dry. Iron on backside. Shrink 1-3%</WashInstruction><WashInstruction locale="de">Von links waschen mit ähnlichen Farben. Nicht einweichen. In nassem Zustand in Form ziehen. Hängend trocknen. Von links bügeln. Läuft ein 1-3%</WashInstruction><WashInstruction locale="nl">Binnenste buiten wassen met dezelfde kleuren. Niet weken. In vochtige toestand, voorzichtig op maat rekken. Hangend drogen. Binnenste buiten strijken. Krimp: 1 - 3%.</WashInstruction><WashInstruction locale="sv">Tvättas med avigsidan ut med liknande färger. Undvik blötläggning. Sträcks försiktigt i vått tillstånd. Ska hängtorka. Strykes på baksidan. Krymper: 1 - 3%.</WashInstruction></WashInstructions><IsLive /><LeadPicture><Resource id="134666460816199322_62805" /></LeadPicture><Resources><Resource id="134666460816199322_62805"><OriginalFilename><![CDATA[13102_007210_03_A_0001.jpg]]></OriginalFilename><Year cvl="Year"><![CDATA[13]]></Year><PDMIdentifier /><CatalogAdcode cvl="CatalogAdcode"><value><![CDATA[2013-BAP-PSPR]]></value><value><![CDATA[2013-BAP-SUM]]></value><value><![CDATA[2013-BAP-PAUT]]></value><value><![CDATA[2013-FAV-PSPR]]></value><value><![CDATA[2013-FAV2-SUM]]></value><value><![CDATA[2013-BAP-SPR]]></value><value><![CDATA[2013-PLUS-PSPR]]></value><value><![CDATA[2013-UDS1-SUM]]></value></CatalogAdcode><ImageType cvl="ImageType"><![CDATA[packshots]]></ImageType><ResourceFileId><![CDATA[62805]]></ResourceFileId><MimeType><![CDATA[image/jpeg]]></MimeType><Season cvl="Season"><![CDATA[131]]></Season><AltTexts><AltText locale="da" /><AltText locale="de_CH" /><AltText locale="en" /><AltText locale="de" /><AltText locale="nl" /><AltText locale="sv" /></AltTexts><Filename>D:/inRiver/Publish/Production/Pics/134666460816199322_62805.jpg</Filename></Resource><Resource id="134666460969222388_59402"><OriginalFilename><![CDATA[13102_007210_03_B_0001.jpg]]></OriginalFilename><Year cvl="Year"><![CDATA[13]]></Year><PDMIdentifier /><CatalogAdcode cvl="CatalogAdcode"><value><![CDATA[2013-BAP-PAUT]]></value><value><![CDATA[2013-BAP-PSPR]]></value><value><![CDATA[2013-PLUS-PSPR]]></value><value><![CDATA[2013-FAV-PSPR]]></value><value><![CDATA[2013-BAP-SPR]]></value><value><![CDATA[2013-FAV2-SUM]]></value></CatalogAdcode><ImageType cvl="ImageType"><![CDATA[packshots]]></ImageType><ResourceFileId><![CDATA[59402]]></ResourceFileId><MimeType><![CDATA[image/jpeg]]></MimeType><Season cvl="Season"><![CDATA[131]]></Season><AltTexts><AltText locale="da" /><AltText locale="de_CH" /><AltText locale="en" /><AltText locale="de" /><AltText locale="nl" /><AltText locale="sv" /></AltTexts><Filename>D:/inRiver/Publish/Production/Pics/134666460969222388_59402.jpg</Filename></Resource><Resource id="134666461144294417_59403"><OriginalFilename><![CDATA[13102_007210_03_C_0001.jpg]]></OriginalFilename><Year cvl="Year"><![CDATA[13]]></Year><PDMIdentifier /><CatalogAdcode cvl="CatalogAdcode"><value><![CDATA[2013-BAP-PAUT]]></value><value><![CDATA[2013-BAP-PSPR]]></value><value><![CDATA[2013-PLUS-PSPR]]></value><value><![CDATA[2013-FAV-PSPR]]></value><value><![CDATA[2013-BAP-SPR]]></value><value><![CDATA[2013-FAV2-SUM]]></value></CatalogAdcode><ImageType cvl="ImageType"><![CDATA[packshots]]></ImageType><ResourceFileId><![CDATA[59403]]></ResourceFileId><MimeType><![CDATA[image/jpeg]]></MimeType><Season cvl="Season"><![CDATA[131]]></Season><AltTexts><AltText locale="da" /><AltText locale="de_CH" /><AltText locale="en" /><AltText locale="de" /><AltText locale="nl" /><AltText locale="sv" /></AltTexts><Filename>D:/inRiver/Publish/Production/Pics/134666461144294417_59403.jpg</Filename></Resource><Resource id="134666461247489021_59404"><OriginalFilename><![CDATA[13102_007210_03_D_0001.jpg]]></OriginalFilename><Year cvl="Year"><![CDATA[13]]></Year><PDMIdentifier /><CatalogAdcode cvl="CatalogAdcode"><value><![CDATA[2013-BAP-PAUT]]></value><value><![CDATA[2013-BAP-PSPR]]></value><value><![CDATA[2013-PLUS-PSPR]]></value><value><![CDATA[2013-FAV-PSPR]]></value><value><![CDATA[2013-BAP-SPR]]></value><value><![CDATA[2013-FAV2-SUM]]></value></CatalogAdcode><ImageType cvl="ImageType"><![CDATA[packshots]]></ImageType><ResourceFileId><![CDATA[59404]]></ResourceFileId><MimeType><![CDATA[image/jpeg]]></MimeType><Season cvl="Season"><![CDATA[131]]></Season><AltTexts><AltText locale="da" /><AltText locale="de_CH" /><AltText locale="en" /><AltText locale="de" /><AltText locale="nl" /><AltText locale="sv" /></AltTexts><Filename>D:/inRiver/Publish/Production/Pics/134666461247489021_59404.jpg</Filename></Resource><Resource id="134752799318974171_49782"><OriginalFilename><![CDATA[131B_ALT_17_V036.jpg]]></OriginalFilename><Year cvl="Year"><![CDATA[13]]></Year><PDMIdentifier /><CatalogAdcode cvl="CatalogAdcode" /><ImageType cvl="ImageType"><![CDATA[modelshots]]></ImageType><ResourceFileId><![CDATA[49782]]></ResourceFileId><MimeType><![CDATA[image/jpeg]]></MimeType><Season cvl="Season"><![CDATA[131]]></Season><AltTexts><AltText locale="da" /><AltText locale="de_CH" /><AltText locale="en" /><AltText locale="de" /><AltText locale="nl" /><AltText locale="sv" /></AltTexts><Filename>D:/inRiver/Publish/Production/Pics/134752799318974171_49782.jpg</Filename></Resource><Resource id="13475280042363880_56077"><OriginalFilename><![CDATA[131B_ALT_58_V004.jpg]]></OriginalFilename><Year cvl="Year"><![CDATA[13]]></Year><PDMIdentifier /><CatalogAdcode cvl="CatalogAdcode" /><ImageType cvl="ImageType"><![CDATA[modelshots]]></ImageType><ResourceFileId><![CDATA[56077]]></ResourceFileId><MimeType><![CDATA[image/jpeg]]></MimeType><Season cvl="Season"><![CDATA[131]]></Season><AltTexts><AltText locale="da" /><AltText locale="de_CH" /><AltText locale="en" /><AltText locale="de" /><AltText locale="nl" /><AltText locale="sv" /></AltTexts><Filename>D:/inRiver/Publish/Production/Pics/13475280042363880_56077.jpg</Filename></Resource><Resource id="134812353317168909_50012"><OriginalFilename><![CDATA[131B_33_01_V093.jpg]]></OriginalFilename><Year cvl="Year"><![CDATA[13]]></Year><PDMIdentifier /><CatalogAdcode cvl="CatalogAdcode"><value><![CDATA[2013-BAP-PSPR]]></value></CatalogAdcode><ImageType cvl="ImageType"><![CDATA[modelshots]]></ImageType><ResourceFileId><![CDATA[50012]]></ResourceFileId><MimeType><![CDATA[image/jpeg]]></MimeType><Season cvl="Season"><![CDATA[131]]></Season><AltTexts><AltText locale="da" /><AltText locale="de_CH" /><AltText locale="en" /><AltText locale="de" /><AltText locale="nl" /><AltText locale="sv" /></AltTexts><Filename>D:/inRiver/Publish/Production/Pics/134812353317168909_50012.jpg</Filename></Resource><Resource id="134812355026436134_50072"><OriginalFilename><![CDATA[131B_21_02_V051.jpg]]></OriginalFilename><Year cvl="Year"><![CDATA[13]]></Year><PDMIdentifier /><CatalogAdcode cvl="CatalogAdcode"><value><![CDATA[2013-BAP-PSPR]]></value></CatalogAdcode><ImageType cvl="ImageType"><![CDATA[modelshots]]></ImageType><ResourceFileId><![CDATA[50072]]></ResourceFileId><MimeType><![CDATA[image/jpeg]]></MimeType><Season cvl="Season"><![CDATA[131]]></Season><AltTexts><AltText locale="da" /><AltText locale="de_CH" /><AltText locale="en" /><AltText locale="de" /><AltText locale="nl" /><AltText locale="sv" /></AltTexts><Filename>D:/inRiver/Publish/Production/Pics/134812355026436134_50072.jpg</Filename></Resource></Resources></Item></Items><Assortments><Assortment id="134555882434746218" order="14" /><Assortment id="134555884395669202" order="24" /><Assortment id="134555884669123927" order="0" /></Assortments><Resources><Resource id="134666460816199322_62805"><OriginalFilename><![CDATA[13102_007210_03_A_0001.jpg]]></OriginalFilename><Year cvl="Year"><![CDATA[13]]></Year><PDMIdentifier /><CatalogAdcode cvl="CatalogAdcode"><value><![CDATA[2013-BAP-PSPR]]></value><value><![CDATA[2013-BAP-SUM]]></value><value><![CDATA[2013-BAP-PAUT]]></value><value><![CDATA[2013-FAV-PSPR]]></value><value><![CDATA[2013-FAV2-SUM]]></value><value><![CDATA[2013-BAP-SPR]]></value><value><![CDATA[2013-PLUS-PSPR]]></value><value><![CDATA[2013-UDS1-SUM]]></value></CatalogAdcode><ImageType cvl="ImageType"><![CDATA[packshots]]></ImageType><ResourceFileId><![CDATA[62805]]></ResourceFileId><MimeType><![CDATA[image/jpeg]]></MimeType><Season cvl="Season"><![CDATA[131]]></Season><AltTexts><AltText locale="da" /><AltText locale="de_CH" /><AltText locale="en" /><AltText locale="de" /><AltText locale="nl" /><AltText locale="sv" /></AltTexts><Filename>D:/inRiver/Publish/Production/Pics/134666460816199322_62805.jpg</Filename></Resource><Resource id="134666460969222388_59402"><OriginalFilename><![CDATA[13102_007210_03_B_0001.jpg]]></OriginalFilename><Year cvl="Year"><![CDATA[13]]></Year><PDMIdentifier /><CatalogAdcode cvl="CatalogAdcode"><value><![CDATA[2013-BAP-PAUT]]></value><value><![CDATA[2013-BAP-PSPR]]></value><value><![CDATA[2013-PLUS-PSPR]]></value><value><![CDATA[2013-FAV-PSPR]]></value><value><![CDATA[2013-BAP-SPR]]></value><value><![CDATA[2013-FAV2-SUM]]></value></CatalogAdcode><ImageType cvl="ImageType"><![CDATA[packshots]]></ImageType><ResourceFileId><![CDATA[59402]]></ResourceFileId><MimeType><![CDATA[image/jpeg]]></MimeType><Season cvl="Season"><![CDATA[131]]></Season><AltTexts><AltText locale="da" /><AltText locale="de_CH" /><AltText locale="en" /><AltText locale="de" /><AltText locale="nl" /><AltText locale="sv" /></AltTexts><Filename>D:/inRiver/Publish/Production/Pics/134666460969222388_59402.jpg</Filename></Resource><Resource id="134666461144294417_59403"><OriginalFilename><![CDATA[13102_007210_03_C_0001.jpg]]></OriginalFilename><Year cvl="Year"><![CDATA[13]]></Year><PDMIdentifier /><CatalogAdcode cvl="CatalogAdcode"><value><![CDATA[2013-BAP-PAUT]]></value><value><![CDATA[2013-BAP-PSPR]]></value><value><![CDATA[2013-PLUS-PSPR]]></value><value><![CDATA[2013-FAV-PSPR]]></value><value><![CDATA[2013-BAP-SPR]]></value><value><![CDATA[2013-FAV2-SUM]]></value></CatalogAdcode><ImageType cvl="ImageType"><![CDATA[packshots]]></ImageType><ResourceFileId><![CDATA[59403]]></ResourceFileId><MimeType><![CDATA[image/jpeg]]></MimeType><Season cvl="Season"><![CDATA[131]]></Season><AltTexts><AltText locale="da" /><AltText locale="de_CH" /><AltText locale="en" /><AltText locale="de" /><AltText locale="nl" /><AltText locale="sv" /></AltTexts><Filename>D:/inRiver/Publish/Production/Pics/134666461144294417_59403.jpg</Filename></Resource><Resource id="134666461247489021_59404"><OriginalFilename><![CDATA[13102_007210_03_D_0001.jpg]]></OriginalFilename><Year cvl="Year"><![CDATA[13]]></Year><PDMIdentifier /><CatalogAdcode cvl="CatalogAdcode"><value><![CDATA[2013-BAP-PAUT]]></value><value><![CDATA[2013-BAP-PSPR]]></value><value><![CDATA[2013-PLUS-PSPR]]></value><value><![CDATA[2013-FAV-PSPR]]></value><value><![CDATA[2013-BAP-SPR]]></value><value><![CDATA[2013-FAV2-SUM]]></value></CatalogAdcode><ImageType cvl="ImageType"><![CDATA[packshots]]></ImageType><ResourceFileId><![CDATA[59404]]></ResourceFileId><MimeType><![CDATA[image/jpeg]]></MimeType><Season cvl="Season"><![CDATA[131]]></Season><AltTexts><AltText locale="da" /><AltText locale="de_CH" /><AltText locale="en" /><AltText locale="de" /><AltText locale="nl" /><AltText locale="sv" /></AltTexts><Filename>D:/inRiver/Publish/Production/Pics/134666461247489021_59404.jpg</Filename></Resource></Resources></Product>
